<?xml version="1.0" encoding="UTF-8"?>
<spirit:component xmlns:xilinx="http://www.xilinx.com" xmlns:spirit="http://www.spiritconsortium.org/XMLSchema/SPIRIT/1685-2009" xmlns:xsi="http://www.w3.org/2001/XMLSchema-instance">
  <spirit:vendor>specnext.com</spirit:vendor>
  <spirit:library>specnext</spirit:library>
  <spirit:name>zxvideo</spirit:name>
  <spirit:version>1.0</spirit:version>
  <spirit:busInterfaces>
    <spirit:busInterface>
      <spirit:name>reset</spirit:name>
      <spirit:busType spirit:vendor="xilinx.com" spirit:library="signal" spirit:name="reset" spirit:version="1.0"/>
      <spirit:abstractionType spirit:vendor="xilinx.com" spirit:library="signal" spirit:name="reset_rtl" spirit:version="1.0"/>
      <spirit:slave/>
      <spirit:portMaps>
        <spirit:portMap>
          <spirit:logicalPort>
            <spirit:name>RST</spirit:name>
          </spirit:logicalPort>
          <spirit:physicalPort>
            <spirit:name>reset</spirit:name>
          </spirit:physicalPort>
        </spirit:portMap>
      </spirit:portMaps>
      <spirit:parameters>
        <spirit:parameter>
          <spirit:name>POLARITY</spirit:name>
          <spirit:value spirit:id="BUSIFPARAM_VALUE.RESET.POLARITY">ACTIVE_HIGH</spirit:value>
        </spirit:parameter>
      </spirit:parameters>
    </spirit:busInterface>
    <spirit:busInterface>
      <spirit:name>video</spirit:name>
      <spirit:busType spirit:vendor="specnext.com" spirit:library="specnext" spirit:name="video" spirit:version="1.0"/>
      <spirit:abstractionType spirit:vendor="specnext.com" spirit:library="specnext" spirit:name="video_rtl" spirit:version="1.0"/>
      <spirit:slave/>
      <spirit:portMaps>
        <spirit:portMap>
          <spirit:logicalPort>
            <spirit:name>scanlines</spirit:name>
          </spirit:logicalPort>
          <spirit:physicalPort>
            <spirit:name>scanlines</spirit:name>
          </spirit:physicalPort>
        </spirit:portMap>
        <spirit:portMap>
          <spirit:logicalPort>
            <spirit:name>scandouble</spirit:name>
          </spirit:logicalPort>
          <spirit:physicalPort>
            <spirit:name>scandouble</spirit:name>
          </spirit:physicalPort>
        </spirit:portMap>
        <spirit:portMap>
          <spirit:logicalPort>
            <spirit:name>freq_50_60</spirit:name>
          </spirit:logicalPort>
          <spirit:physicalPort>
            <spirit:name>freq_50_60</spirit:name>
          </spirit:physicalPort>
        </spirit:portMap>
        <spirit:portMap>
          <spirit:logicalPort>
            <spirit:name>machine_timing</spirit:name>
          </spirit:logicalPort>
          <spirit:physicalPort>
            <spirit:name>machine_timing</spirit:name>
          </spirit:physicalPort>
        </spirit:portMap>
        <spirit:portMap>
          <spirit:logicalPort>
            <spirit:name>hblank_n</spirit:name>
          </spirit:logicalPort>
          <spirit:physicalPort>
            <spirit:name>hblank_n</spirit:name>
          </spirit:physicalPort>
        </spirit:portMap>
        <spirit:portMap>
          <spirit:logicalPort>
            <spirit:name>video_mode</spirit:name>
          </spirit:logicalPort>
          <spirit:physicalPort>
            <spirit:name>video_mode</spirit:name>
          </spirit:physicalPort>
        </spirit:portMap>
        <spirit:portMap>
          <spirit:logicalPort>
            <spirit:name>rgb</spirit:name>
          </spirit:logicalPort>
          <spirit:physicalPort>
            <spirit:name>rgb</spirit:name>
          </spirit:physicalPort>
        </spirit:portMap>
        <spirit:portMap>
          <spirit:logicalPort>
            <spirit:name>vblank_n</spirit:name>
          </spirit:logicalPort>
          <spirit:physicalPort>
            <spirit:name>vblank_n</spirit:name>
          </spirit:physicalPort>
        </spirit:portMap>
        <spirit:portMap>
          <spirit:logicalPort>
            <spirit:name>csync_n</spirit:name>
          </spirit:logicalPort>
          <spirit:physicalPort>
            <spirit:name>csync_n</spirit:name>
          </spirit:physicalPort>
        </spirit:portMap>
        <spirit:portMap>
          <spirit:logicalPort>
            <spirit:name>hsync_n</spirit:name>
          </spirit:logicalPort>
          <spirit:physicalPort>
            <spirit:name>hsync_n</spirit:name>
          </spirit:physicalPort>
        </spirit:portMap>
        <spirit:portMap>
          <spirit:logicalPort>
            <spirit:name>hdmi_audio_en</spirit:name>
          </spirit:logicalPort>
          <spirit:physicalPort>
            <spirit:name>hdmi_audio_en</spirit:name>
          </spirit:physicalPort>
        </spirit:portMap>
        <spirit:portMap>
          <spirit:logicalPort>
            <spirit:name>vsync_n</spirit:name>
          </spirit:logicalPort>
          <spirit:physicalPort>
            <spirit:name>vsync_n</spirit:name>
          </spirit:physicalPort>
        </spirit:portMap>
        <spirit:portMap>
          <spirit:logicalPort>
            <spirit:name>hdmi_reset</spirit:name>
          </spirit:logicalPort>
          <spirit:physicalPort>
            <spirit:name>hdmi_reset</spirit:name>
          </spirit:physicalPort>
        </spirit:portMap>
      </spirit:portMaps>
    </spirit:busInterface>
    <spirit:busInterface>
      <spirit:name>clk_video</spirit:name>
      <spirit:busType spirit:vendor="xilinx.com" spirit:library="signal" spirit:name="clock" spirit:version="1.0"/>
      <spirit:abstractionType spirit:vendor="xilinx.com" spirit:library="signal" spirit:name="clock_rtl" spirit:version="1.0"/>
      <spirit:slave/>
      <spirit:portMaps>
        <spirit:portMap>
          <spirit:logicalPort>
            <spirit:name>CLK</spirit:name>
          </spirit:logicalPort>
          <spirit:physicalPort>
            <spirit:name>clk_video</spirit:name>
          </spirit:physicalPort>
        </spirit:portMap>
      </spirit:portMaps>
      <spirit:parameters>
        <spirit:parameter>
          <spirit:name>ASSOCIATED_RESET</spirit:name>
          <spirit:value spirit:id="BUSIFPARAM_VALUE.CLK_VIDEO.ASSOCIATED_RESET"/>
        </spirit:parameter>
      </spirit:parameters>
    </spirit:busInterface>
    <spirit:busInterface>
      <spirit:name>clk_peripheral</spirit:name>
      <spirit:busType spirit:vendor="xilinx.com" spirit:library="signal" spirit:name="clock" spirit:version="1.0"/>
      <spirit:abstractionType spirit:vendor="xilinx.com" spirit:library="signal" spirit:name="clock_rtl" spirit:version="1.0"/>
      <spirit:slave/>
      <spirit:portMaps>
        <spirit:portMap>
          <spirit:logicalPort>
            <spirit:name>CLK</spirit:name>
          </spirit:logicalPort>
          <spirit:physicalPort>
            <spirit:name>clk_peripheral</spirit:name>
          </spirit:physicalPort>
        </spirit:portMap>
      </spirit:portMaps>
      <spirit:parameters>
        <spirit:parameter>
          <spirit:name>ASSOCIATED_RESET</spirit:name>
          <spirit:value spirit:id="BUSIFPARAM_VALUE.CLK_PERIPHERAL.ASSOCIATED_RESET">reset</spirit:value>
        </spirit:parameter>
      </spirit:parameters>
    </spirit:busInterface>
  </spirit:busInterfaces>
  <spirit:model>
    <spirit:views>
      <spirit:view>
        <spirit:name>xilinx_anylanguagesynthesis</spirit:name>
        <spirit:displayName>Synthesis</spirit:displayName>
        <spirit:envIdentifier>:vivado.xilinx.com:synthesis</spirit:envIdentifier>
        <spirit:language>Verilog</spirit:language>
        <spirit:modelName>zxvideo</spirit:modelName>
        <spirit:fileSetRef>
          <spirit:localName>xilinx_anylanguagesynthesis_view_fileset</spirit:localName>
        </spirit:fileSetRef>
        <spirit:parameters>
          <spirit:parameter>
            <spirit:name>viewChecksum</spirit:name>
            <spirit:value>b550473e</spirit:value>
          </spirit:parameter>
        </spirit:parameters>
      </spirit:view>
      <spirit:view>
        <spirit:name>xilinx_anylanguagebehavioralsimulation</spirit:name>
        <spirit:displayName>Simulation</spirit:displayName>
        <spirit:envIdentifier>:vivado.xilinx.com:simulation</spirit:envIdentifier>
        <spirit:language>Verilog</spirit:language>
        <spirit:modelName>zxvideo</spirit:modelName>
        <spirit:fileSetRef>
          <spirit:localName>xilinx_anylanguagebehavioralsimulation_view_fileset</spirit:localName>
        </spirit:fileSetRef>
        <spirit:parameters>
          <spirit:parameter>
            <spirit:name>viewChecksum</spirit:name>
            <spirit:value>b550473e</spirit:value>
          </spirit:parameter>
        </spirit:parameters>
      </spirit:view>
      <spirit:view>
        <spirit:name>xilinx_xpgui</spirit:name>
        <spirit:displayName>UI Layout</spirit:displayName>
        <spirit:envIdentifier>:vivado.xilinx.com:xgui.ui</spirit:envIdentifier>
        <spirit:fileSetRef>
          <spirit:localName>xilinx_xpgui_view_fileset</spirit:localName>
        </spirit:fileSetRef>
        <spirit:parameters>
          <spirit:parameter>
            <spirit:name>viewChecksum</spirit:name>
            <spirit:value>f64a5dae</spirit:value>
          </spirit:parameter>
        </spirit:parameters>
      </spirit:view>
    </spirit:views>
    <spirit:ports>
      <spirit:port>
        <spirit:name>r</spirit:name>
        <spirit:wire>
          <spirit:direction>out</spirit:direction>
          <spirit:vector>
            <spirit:left spirit:format="long">3</spirit:left>
            <spirit:right spirit:format="long">0</spirit:right>
          </spirit:vector>
          <spirit:wireTypeDefs>
            <spirit:wireTypeDef>
              <spirit:typeName>reg</spirit:typeName>
              <spirit:viewNameRef>xilinx_anylanguagesynthesis</spirit:viewNameRef>
              <spirit:viewNameRef>xilinx_anylanguagebehavioralsimulation</spirit:viewNameRef>
            </spirit:wireTypeDef>
          </spirit:wireTypeDefs>
        </spirit:wire>
      </spirit:port>
      <spirit:port>
        <spirit:name>g</spirit:name>
        <spirit:wire>
          <spirit:direction>out</spirit:direction>
          <spirit:vector>
            <spirit:left spirit:format="long">3</spirit:left>
            <spirit:right spirit:format="long">0</spirit:right>
          </spirit:vector>
          <spirit:wireTypeDefs>
            <spirit:wireTypeDef>
              <spirit:typeName>reg</spirit:typeName>
              <spirit:viewNameRef>xilinx_anylanguagesynthesis</spirit:viewNameRef>
              <spirit:viewNameRef>xilinx_anylanguagebehavioralsimulation</spirit:viewNameRef>
            </spirit:wireTypeDef>
          </spirit:wireTypeDefs>
        </spirit:wire>
      </spirit:port>
      <spirit:port>
        <spirit:name>b</spirit:name>
        <spirit:wire>
          <spirit:direction>out</spirit:direction>
          <spirit:vector>
            <spirit:left spirit:format="long">3</spirit:left>
            <spirit:right spirit:format="long">0</spirit:right>
          </spirit:vector>
          <spirit:wireTypeDefs>
            <spirit:wireTypeDef>
              <spirit:typeName>reg</spirit:typeName>
              <spirit:viewNameRef>xilinx_anylanguagesynthesis</spirit:viewNameRef>
              <spirit:viewNameRef>xilinx_anylanguagebehavioralsimulation</spirit:viewNameRef>
            </spirit:wireTypeDef>
          </spirit:wireTypeDefs>
        </spirit:wire>
      </spirit:port>
      <spirit:port>
        <spirit:name>hs</spirit:name>
        <spirit:wire>
          <spirit:direction>out</spirit:direction>
          <spirit:wireTypeDefs>
            <spirit:wireTypeDef>
              <spirit:typeName>std_logic</spirit:typeName>
              <spirit:viewNameRef>xilinx_anylanguagesynthesis</spirit:viewNameRef>
              <spirit:viewNameRef>xilinx_anylanguagebehavioralsimulation</spirit:viewNameRef>
            </spirit:wireTypeDef>
          </spirit:wireTypeDefs>
        </spirit:wire>
      </spirit:port>
      <spirit:port>
        <spirit:name>vs</spirit:name>
        <spirit:wire>
          <spirit:direction>out</spirit:direction>
          <spirit:wireTypeDefs>
            <spirit:wireTypeDef>
              <spirit:typeName>std_logic</spirit:typeName>
              <spirit:viewNameRef>xilinx_anylanguagesynthesis</spirit:viewNameRef>
              <spirit:viewNameRef>xilinx_anylanguagebehavioralsimulation</spirit:viewNameRef>
            </spirit:wireTypeDef>
          </spirit:wireTypeDefs>
        </spirit:wire>
      </spirit:port>
      <spirit:port>
        <spirit:name>rgb</spirit:name>
        <spirit:wire>
          <spirit:direction>in</spirit:direction>
          <spirit:vector>
            <spirit:left spirit:format="long">8</spirit:left>
            <spirit:right spirit:format="long">0</spirit:right>
          </spirit:vector>
          <spirit:wireTypeDefs>
            <spirit:wireTypeDef>
              <spirit:typeName>std_logic_vector</spirit:typeName>
              <spirit:viewNameRef>xilinx_anylanguagesynthesis</spirit:viewNameRef>
              <spirit:viewNameRef>xilinx_anylanguagebehavioralsimulation</spirit:viewNameRef>
            </spirit:wireTypeDef>
          </spirit:wireTypeDefs>
          <spirit:driver>
            <spirit:defaultValue spirit:format="long">0</spirit:defaultValue>
          </spirit:driver>
        </spirit:wire>
      </spirit:port>
      <spirit:port>
        <spirit:name>csync_n</spirit:name>
        <spirit:wire>
          <spirit:direction>in</spirit:direction>
          <spirit:wireTypeDefs>
            <spirit:wireTypeDef>
              <spirit:typeName>std_logic</spirit:typeName>
              <spirit:viewNameRef>xilinx_anylanguagesynthesis</spirit:viewNameRef>
              <spirit:viewNameRef>xilinx_anylanguagebehavioralsimulation</spirit:viewNameRef>
            </spirit:wireTypeDef>
          </spirit:wireTypeDefs>
          <spirit:driver>
            <spirit:defaultValue spirit:format="long">1</spirit:defaultValue>
          </spirit:driver>
        </spirit:wire>
      </spirit:port>
      <spirit:port>
        <spirit:name>vsync_n</spirit:name>
        <spirit:wire>
          <spirit:direction>in</spirit:direction>
          <spirit:wireTypeDefs>
            <spirit:wireTypeDef>
              <spirit:typeName>std_logic</spirit:typeName>
              <spirit:viewNameRef>xilinx_anylanguagesynthesis</spirit:viewNameRef>
              <spirit:viewNameRef>xilinx_anylanguagebehavioralsimulation</spirit:viewNameRef>
            </spirit:wireTypeDef>
          </spirit:wireTypeDefs>
          <spirit:driver>
            <spirit:defaultValue spirit:format="long">1</spirit:defaultValue>
          </spirit:driver>
        </spirit:wire>
      </spirit:port>
      <spirit:port>
        <spirit:name>hsync_n</spirit:name>
        <spirit:wire>
          <spirit:direction>in</spirit:direction>
          <spirit:wireTypeDefs>
            <spirit:wireTypeDef>
              <spirit:typeName>std_logic</spirit:typeName>
              <spirit:viewNameRef>xilinx_anylanguagesynthesis</spirit:viewNameRef>
              <spirit:viewNameRef>xilinx_anylanguagebehavioralsimulation</spirit:viewNameRef>
            </spirit:wireTypeDef>
          </spirit:wireTypeDefs>
          <spirit:driver>
            <spirit:defaultValue spirit:format="long">1</spirit:defaultValue>
          </spirit:driver>
        </spirit:wire>
      </spirit:port>
      <spirit:port>
        <spirit:name>vblank_n</spirit:name>
        <spirit:wire>
          <spirit:direction>in</spirit:direction>
          <spirit:wireTypeDefs>
            <spirit:wireTypeDef>
              <spirit:typeName>std_logic</spirit:typeName>
              <spirit:viewNameRef>xilinx_anylanguagesynthesis</spirit:viewNameRef>
              <spirit:viewNameRef>xilinx_anylanguagebehavioralsimulation</spirit:viewNameRef>
            </spirit:wireTypeDef>
          </spirit:wireTypeDefs>
          <spirit:driver>
            <spirit:defaultValue spirit:format="long">1</spirit:defaultValue>
          </spirit:driver>
        </spirit:wire>
      </spirit:port>
      <spirit:port>
        <spirit:name>hblank_n</spirit:name>
        <spirit:wire>
          <spirit:direction>in</spirit:direction>
          <spirit:wireTypeDefs>
            <spirit:wireTypeDef>
              <spirit:typeName>std_logic</spirit:typeName>
              <spirit:viewNameRef>xilinx_anylanguagesynthesis</spirit:viewNameRef>
              <spirit:viewNameRef>xilinx_anylanguagebehavioralsimulation</spirit:viewNameRef>
            </spirit:wireTypeDef>
          </spirit:wireTypeDefs>
          <spirit:driver>
            <spirit:defaultValue spirit:format="long">1</spirit:defaultValue>
          </spirit:driver>
        </spirit:wire>
      </spirit:port>
      <spirit:port>
        <spirit:name>freq_50_60</spirit:name>
        <spirit:wire>
          <spirit:direction>in</spirit:direction>
          <spirit:wireTypeDefs>
            <spirit:wireTypeDef>
              <spirit:typeName>std_logic</spirit:typeName>
              <spirit:viewNameRef>xilinx_anylanguagesynthesis</spirit:viewNameRef>
              <spirit:viewNameRef>xilinx_anylanguagebehavioralsimulation</spirit:viewNameRef>
            </spirit:wireTypeDef>
          </spirit:wireTypeDefs>
          <spirit:driver>
            <spirit:defaultValue spirit:format="long">0</spirit:defaultValue>
          </spirit:driver>
        </spirit:wire>
      </spirit:port>
      <spirit:port>
        <spirit:name>scanlines</spirit:name>
        <spirit:wire>
          <spirit:direction>in</spirit:direction>
          <spirit:vector>
            <spirit:left spirit:format="long">1</spirit:left>
            <spirit:right spirit:format="long">0</spirit:right>
          </spirit:vector>
          <spirit:wireTypeDefs>
            <spirit:wireTypeDef>
              <spirit:typeName>std_logic_vector</spirit:typeName>
              <spirit:viewNameRef>xilinx_anylanguagesynthesis</spirit:viewNameRef>
              <spirit:viewNameRef>xilinx_anylanguagebehavioralsimulation</spirit:viewNameRef>
            </spirit:wireTypeDef>
          </spirit:wireTypeDefs>
          <spirit:driver>
            <spirit:defaultValue spirit:format="long">0</spirit:defaultValue>
          </spirit:driver>
        </spirit:wire>
      </spirit:port>
      <spirit:port>
        <spirit:name>scandouble</spirit:name>
        <spirit:wire>
          <spirit:direction>in</spirit:direction>
          <spirit:wireTypeDefs>
            <spirit:wireTypeDef>
              <spirit:typeName>std_logic</spirit:typeName>
              <spirit:viewNameRef>xilinx_anylanguagesynthesis</spirit:viewNameRef>
              <spirit:viewNameRef>xilinx_anylanguagebehavioralsimulation</spirit:viewNameRef>
            </spirit:wireTypeDef>
          </spirit:wireTypeDefs>
          <spirit:driver>
            <spirit:defaultValue spirit:format="long">0</spirit:defaultValue>
          </spirit:driver>
        </spirit:wire>
      </spirit:port>
      <spirit:port>
        <spirit:name>video_mode</spirit:name>
        <spirit:wire>
          <spirit:direction>in</spirit:direction>
          <spirit:vector>
            <spirit:left spirit:format="long">2</spirit:left>
            <spirit:right spirit:format="long">0</spirit:right>
          </spirit:vector>
          <spirit:wireTypeDefs>
            <spirit:wireTypeDef>
              <spirit:typeName>std_logic_vector</spirit:typeName>
              <spirit:viewNameRef>xilinx_anylanguagesynthesis</spirit:viewNameRef>
              <spirit:viewNameRef>xilinx_anylanguagebehavioralsimulation</spirit:viewNameRef>
            </spirit:wireTypeDef>
          </spirit:wireTypeDefs>
          <spirit:driver>
            <spirit:defaultValue spirit:format="long">0</spirit:defaultValue>
          </spirit:driver>
        </spirit:wire>
      </spirit:port>
      <spirit:port>
        <spirit:name>machine_timing</spirit:name>
        <spirit:wire>
          <spirit:direction>in</spirit:direction>
          <spirit:vector>
            <spirit:left spirit:format="long">2</spirit:left>
            <spirit:right spirit:format="long">0</spirit:right>
          </spirit:vector>
          <spirit:wireTypeDefs>
            <spirit:wireTypeDef>
              <spirit:typeName>std_logic_vector</spirit:typeName>
              <spirit:viewNameRef>xilinx_anylanguagesynthesis</spirit:viewNameRef>
              <spirit:viewNameRef>xilinx_anylanguagebehavioralsimulation</spirit:viewNameRef>
            </spirit:wireTypeDef>
          </spirit:wireTypeDefs>
          <spirit:driver>
            <spirit:defaultValue spirit:format="long">0</spirit:defaultValue>
          </spirit:driver>
        </spirit:wire>
      </spirit:port>
      <spirit:port>
        <spirit:name>hdmi_reset</spirit:name>
        <spirit:wire>
          <spirit:direction>in</spirit:direction>
          <spirit:wireTypeDefs>
            <spirit:wireTypeDef>
              <spirit:typeName>std_logic</spirit:typeName>
              <spirit:viewNameRef>xilinx_anylanguagesynthesis</spirit:viewNameRef>
              <spirit:viewNameRef>xilinx_anylanguagebehavioralsimulation</spirit:viewNameRef>
            </spirit:wireTypeDef>
          </spirit:wireTypeDefs>
          <spirit:driver>
            <spirit:defaultValue spirit:format="long">0</spirit:defaultValue>
          </spirit:driver>
        </spirit:wire>
      </spirit:port>
      <spirit:port>
        <spirit:name>hdmi_audio_en</spirit:name>
        <spirit:wire>
          <spirit:direction>in</spirit:direction>
          <spirit:wireTypeDefs>
            <spirit:wireTypeDef>
              <spirit:typeName>std_logic</spirit:typeName>
              <spirit:viewNameRef>xilinx_anylanguagesynthesis</spirit:viewNameRef>
              <spirit:viewNameRef>xilinx_anylanguagebehavioralsimulation</spirit:viewNameRef>
            </spirit:wireTypeDef>
          </spirit:wireTypeDefs>
          <spirit:driver>
            <spirit:defaultValue spirit:format="long">0</spirit:defaultValue>
          </spirit:driver>
        </spirit:wire>
      </spirit:port>
      <spirit:port>
        <spirit:name>clk_video</spirit:name>
        <spirit:wire>
          <spirit:direction>in</spirit:direction>
          <spirit:wireTypeDefs>
            <spirit:wireTypeDef>
              <spirit:typeName>std_logic</spirit:typeName>
              <spirit:viewNameRef>xilinx_anylanguagesynthesis</spirit:viewNameRef>
              <spirit:viewNameRef>xilinx_anylanguagebehavioralsimulation</spirit:viewNameRef>
            </spirit:wireTypeDef>
          </spirit:wireTypeDefs>
        </spirit:wire>
      </spirit:port>
      <spirit:port>
        <spirit:name>clk_peripheral</spirit:name>
        <spirit:wire>
          <spirit:direction>in</spirit:direction>
          <spirit:wireTypeDefs>
            <spirit:wireTypeDef>
              <spirit:typeName>std_logic</spirit:typeName>
              <spirit:viewNameRef>xilinx_anylanguagesynthesis</spirit:viewNameRef>
              <spirit:viewNameRef>xilinx_anylanguagebehavioralsimulation</spirit:viewNameRef>
            </spirit:wireTypeDef>
          </spirit:wireTypeDefs>
        </spirit:wire>
      </spirit:port>
      <spirit:port>
        <spirit:name>reset</spirit:name>
        <spirit:wire>
          <spirit:direction>in</spirit:direction>
          <spirit:wireTypeDefs>
            <spirit:wireTypeDef>
              <spirit:typeName>std_logic</spirit:typeName>
              <spirit:viewNameRef>xilinx_anylanguagesynthesis</spirit:viewNameRef>
              <spirit:viewNameRef>xilinx_anylanguagebehavioralsimulation</spirit:viewNameRef>
            </spirit:wireTypeDef>
          </spirit:wireTypeDefs>
        </spirit:wire>
      </spirit:port>
    </spirit:ports>
  </spirit:model>
  <spirit:fileSets>
    <spirit:fileSet>
      <spirit:name>xilinx_anylanguagesynthesis_view_fileset</spirit:name>
      <spirit:file>
        <spirit:name>zxvideo.srcs/sources_1/imports/ram/dpram2.vhd</spirit:name>
        <spirit:userFileType>vhdlSource-2008</spirit:userFileType>
      </spirit:file>
      <spirit:file>
        <spirit:name>zxvideo.srcs/sources_1/imports/vga/scan_convert.vhd</spirit:name>
        <spirit:userFileType>vhdlSource-2008</spirit:userFileType>
      </spirit:file>
      <spirit:file>
        <spirit:name>zxvideo.srcs/sources_1/new/zxvideo.v</spirit:name>
        <spirit:fileType>verilogSource</spirit:fileType>
        <spirit:userFileType>CHECKSUM_2e7d6b22</spirit:userFileType>
      </spirit:file>
    </spirit:fileSet>
    <spirit:fileSet>
      <spirit:name>xilinx_anylanguagebehavioralsimulation_view_fileset</spirit:name>
      <spirit:file>
        <spirit:name>zxvideo.srcs/sources_1/imports/ram/dpram2.vhd</spirit:name>
        <spirit:userFileType>vhdlSource-2008</spirit:userFileType>
      </spirit:file>
      <spirit:file>
        <spirit:name>zxvideo.srcs/sources_1/imports/vga/scan_convert.vhd</spirit:name>
        <spirit:userFileType>vhdlSource-2008</spirit:userFileType>
      </spirit:file>
      <spirit:file>
        <spirit:name>zxvideo.srcs/sources_1/new/zxvideo.v</spirit:name>
        <spirit:fileType>verilogSource</spirit:fileType>
      </spirit:file>
    </spirit:fileSet>
    <spirit:fileSet>
      <spirit:name>xilinx_xpgui_view_fileset</spirit:name>
      <spirit:file>
        <spirit:name>xgui/zxvideo_v1_0.tcl</spirit:name>
        <spirit:fileType>tclSource</spirit:fileType>
        <spirit:userFileType>CHECKSUM_f64a5dae</spirit:userFileType>
        <spirit:userFileType>XGUI_VERSION_2</spirit:userFileType>
      </spirit:file>
    </spirit:fileSet>
  </spirit:fileSets>
  <spirit:description>zxvideo_v1_0</spirit:description>
  <spirit:parameters>
    <spirit:parameter>
      <spirit:name>Component_Name</spirit:name>
      <spirit:value spirit:resolve="user" spirit:id="PARAM_VALUE.Component_Name" spirit:order="1">zxvideo_v1_0</spirit:value>
    </spirit:parameter>
  </spirit:parameters>
  <spirit:vendorExtensions>
    <xilinx:coreExtensions>
      <xilinx:supportedFamilies>
        <xilinx:family xilinx:lifeCycle="Production">virtex7</xilinx:family>
        <xilinx:family xilinx:lifeCycle="Production">qvirtex7</xilinx:family>
        <xilinx:family xilinx:lifeCycle="Production">versal</xilinx:family>
        <xilinx:family xilinx:lifeCycle="Production">kintex7</xilinx:family>
        <xilinx:family xilinx:lifeCycle="Production">kintex7l</xilinx:family>
        <xilinx:family xilinx:lifeCycle="Production">qkintex7</xilinx:family>
        <xilinx:family xilinx:lifeCycle="Production">qkintex7l</xilinx:family>
        <xilinx:family xilinx:lifeCycle="Production">akintex7</xilinx:family>
        <xilinx:family xilinx:lifeCycle="Production">artix7</xilinx:family>
        <xilinx:family xilinx:lifeCycle="Production">artix7l</xilinx:family>
        <xilinx:family xilinx:lifeCycle="Production">aartix7</xilinx:family>
        <xilinx:family xilinx:lifeCycle="Production">qartix7</xilinx:family>
        <xilinx:family xilinx:lifeCycle="Production">zynq</xilinx:family>
        <xilinx:family xilinx:lifeCycle="Production">qzynq</xilinx:family>
        <xilinx:family xilinx:lifeCycle="Production">azynq</xilinx:family>
        <xilinx:family xilinx:lifeCycle="Production">spartan7</xilinx:family>
        <xilinx:family xilinx:lifeCycle="Production">aspartan7</xilinx:family>
        <xilinx:family xilinx:lifeCycle="Production">virtexu</xilinx:family>
        <xilinx:family xilinx:lifeCycle="Production">zynquplus</xilinx:family>
        <xilinx:family xilinx:lifeCycle="Production">virtexuplus</xilinx:family>
        <xilinx:family xilinx:lifeCycle="Production">virtexuplusHBM</xilinx:family>
        <xilinx:family xilinx:lifeCycle="Production">virtexuplus58g</xilinx:family>
        <xilinx:family xilinx:lifeCycle="Production">kintexuplus</xilinx:family>
        <xilinx:family xilinx:lifeCycle="Production">kintexu</xilinx:family>
      </xilinx:supportedFamilies>
      <xilinx:taxonomies>
        <xilinx:taxonomy>/specnext</xilinx:taxonomy>
      </xilinx:taxonomies>
      <xilinx:displayName>zxvideo_v1_0</xilinx:displayName>
      <xilinx:definitionSource>package_project</xilinx:definitionSource>
      <xilinx:coreRevision>14</xilinx:coreRevision>
      <xilinx:coreCreationDateTime>2021-11-28T15:33:46Z</xilinx:coreCreationDateTime>
      <xilinx:tags>
        <xilinx:tag xilinx:name="ui.data.coregen.df@c23a471_ARCHIVE_LOCATION">v:/zxnext/zxvideo</xilinx:tag>
        <xilinx:tag xilinx:name="ui.data.coregen.df@c40a0b0_ARCHIVE_LOCATION">v:/zxnext/zxvideo</xilinx:tag>
        <xilinx:tag xilinx:name="ui.data.coregen.df@2c1098a3_ARCHIVE_LOCATION">v:/zxnext/zxvideo</xilinx:tag>
        <xilinx:tag xilinx:name="ui.data.coregen.df@7220f40c_ARCHIVE_LOCATION">v:/zxnext/zxvideo</xilinx:tag>
        <xilinx:tag xilinx:name="ui.data.coregen.df@e6cc6_ARCHIVE_LOCATION">v:/zxnext/zxvideo</xilinx:tag>
        <xilinx:tag xilinx:name="ui.data.coregen.df@f16f0aa_ARCHIVE_LOCATION">v:/zxnext/zxvideo</xilinx:tag>
        <xilinx:tag xilinx:name="ui.data.coregen.df@4d1942d9_ARCHIVE_LOCATION">v:/zxnext/zxvideo</xilinx:tag>
        <xilinx:tag xilinx:name="ui.data.coregen.df@5c0f0391_ARCHIVE_LOCATION">v:/zxnext/zxvideo</xilinx:tag>
        <xilinx:tag xilinx:name="ui.data.coregen.df@720bde8a_ARCHIVE_LOCATION">v:/zxnext/zxvideo</xilinx:tag>
        <xilinx:tag xilinx:name="ui.data.coregen.df@f567a79_ARCHIVE_LOCATION">v:/zxnext/zxvideo</xilinx:tag>
        <xilinx:tag xilinx:name="ui.data.coregen.df@1a46be24_ARCHIVE_LOCATION">v:/zxnext/zxvideo</xilinx:tag>
        <xilinx:tag xilinx:name="ui.data.coregen.df@2fd01777_ARCHIVE_LOCATION">v:/zxnext/zxvideo</xilinx:tag>
        <xilinx:tag xilinx:name="ui.data.coregen.df@73a6a85b_ARCHIVE_LOCATION">v:/zxnext/zxvideo</xilinx:tag>
        <xilinx:tag xilinx:name="ui.data.coregen.df@51254be2_ARCHIVE_LOCATION">v:/zxnext/zxvideo</xilinx:tag>
        <xilinx:tag xilinx:name="ui.data.coregen.df@3105a54_ARCHIVE_LOCATION">v:/zxnext/zxvideo</xilinx:tag>
        <xilinx:tag xilinx:name="ui.data.coregen.df@5dd9b061_ARCHIVE_LOCATION">v:/zxnext/zxvideo</xilinx:tag>
        <xilinx:tag xilinx:name="ui.data.coregen.df@3bfbfed4_ARCHIVE_LOCATION">v:/zxnext/zxvideo</xilinx:tag>
        <xilinx:tag xilinx:name="ui.data.coregen.df@151fa8db_ARCHIVE_LOCATION">v:/zxnext/zxvideo</xilinx:tag>
        <xilinx:tag xilinx:name="ui.data.coregen.df@f91f6fe_ARCHIVE_LOCATION">v:/zxnext/zxvideo</xilinx:tag>
        <xilinx:tag xilinx:name="ui.data.coregen.df@33b1e83_ARCHIVE_LOCATION">v:/zxnext/zxvideo</xilinx:tag>
        <xilinx:tag xilinx:name="ui.data.coregen.df@732c3f36_ARCHIVE_LOCATION">v:/zxnext/zxvideo</xilinx:tag>
        <xilinx:tag xilinx:name="ui.data.coregen.df@70f6593e_ARCHIVE_LOCATION">v:/zxnext/zxvideo</xilinx:tag>
        <xilinx:tag xilinx:name="ui.data.coregen.df@7f976a1e_ARCHIVE_LOCATION">v:/zxnext/zxvideo</xilinx:tag>
        <xilinx:tag xilinx:name="ui.data.coregen.df@205a459a_ARCHIVE_LOCATION">v:/zxnext/zxvideo</xilinx:tag>
        <xilinx:tag xilinx:name="ui.data.coregen.df@2362b75f_ARCHIVE_LOCATION">v:/zxnext/zxvideo</xilinx:tag>
        <xilinx:tag xilinx:name="ui.data.coregen.df@186cf26a_ARCHIVE_LOCATION">v:/zxnext/zxvideo</xilinx:tag>
        <xilinx:tag xilinx:name="ui.data.coregen.df@60e0a0fe_ARCHIVE_LOCATION">v:/zxnext/zxvideo</xilinx:tag>
        <xilinx:tag xilinx:name="ui.data.coregen.df@23164afa_ARCHIVE_LOCATION">v:/zxnext/zxvideo</xilinx:tag>
        <xilinx:tag xilinx:name="ui.data.coregen.df@5f74cac7_ARCHIVE_LOCATION">v:/zxnext/zxvideo</xilinx:tag>
        <xilinx:tag xilinx:name="ui.data.coregen.df@3033a149_ARCHIVE_LOCATION">v:/zxnext/zxvideo</xilinx:tag>
        <xilinx:tag xilinx:name="ui.data.coregen.df@170d238b_ARCHIVE_LOCATION">v:/zxnext/zxvideo</xilinx:tag>
        <xilinx:tag xilinx:name="ui.data.coregen.df@2fc8aa06_ARCHIVE_LOCATION">v:/zxnext/zxvideo</xilinx:tag>
        <xilinx:tag xilinx:name="ui.data.coregen.df@d65e41b_ARCHIVE_LOCATION">v:/zxnext/zxvideo</xilinx:tag>
        <xilinx:tag xilinx:name="ui.data.coregen.df@adb2f63_ARCHIVE_LOCATION">v:/zxnext/zxvideo</xilinx:tag>
        <xilinx:tag xilinx:name="ui.data.coregen.df@38f2c20a_ARCHIVE_LOCATION">v:/zxnext/zxvideo</xilinx:tag>
        <xilinx:tag xilinx:name="ui.data.coregen.df@4a6039c2_ARCHIVE_LOCATION">v:/zxnext/zxvideo</xilinx:tag>
        <xilinx:tag xilinx:name="ui.data.coregen.df@1b3171e7_ARCHIVE_LOCATION">v:/zxnext/zxvideo</xilinx:tag>
        <xilinx:tag xilinx:name="ui.data.coregen.df@39b5a958_ARCHIVE_LOCATION">v:/zxnext/zxvideo</xilinx:tag>
        <xilinx:tag xilinx:name="ui.data.coregen.df@52b9bbf3_ARCHIVE_LOCATION">v:/zxnext/zxvideo</xilinx:tag>
        <xilinx:tag xilinx:name="ui.data.coregen.df@4d532f70_ARCHIVE_LOCATION">v:/zxnext/zxvideo</xilinx:tag>
        <xilinx:tag xilinx:name="ui.data.coregen.df@1dbe5594_ARCHIVE_LOCATION">v:/zxnext/zxvideo</xilinx:tag>
        <xilinx:tag xilinx:name="ui.data.coregen.df@66a30c5b_ARCHIVE_LOCATION">v:/zxnext/zxvideo</xilinx:tag>
        <xilinx:tag xilinx:name="ui.data.coregen.df@455997a2_ARCHIVE_LOCATION">v:/zxnext/zxvideo</xilinx:tag>
        <xilinx:tag xilinx:name="ui.data.coregen.df@7da155f1_ARCHIVE_LOCATION">v:/zxnext/zxvideo</xilinx:tag>
        <xilinx:tag xilinx:name="ui.data.coregen.df@6acddde8_ARCHIVE_LOCATION">v:/zxnext/zxvideo</xilinx:tag>
        <xilinx:tag xilinx:name="ui.data.coregen.df@6ab8764c_ARCHIVE_LOCATION">v:/zxnext/zxvideo</xilinx:tag>
        <xilinx:tag xilinx:name="ui.data.coregen.df@b9fde14_ARCHIVE_LOCATION">v:/zxnext/zxvideo</xilinx:tag>
        <xilinx:tag xilinx:name="ui.data.coregen.df@6283238c_ARCHIVE_LOCATION">v:/zxnext/zxvideo</xilinx:tag>
        <xilinx:tag xilinx:name="ui.data.coregen.df@fff5f04_ARCHIVE_LOCATION">v:/zxnext/zxvideo</xilinx:tag>
        <xilinx:tag xilinx:name="ui.data.coregen.df@742fe4ed_ARCHIVE_LOCATION">v:/zxnext/zxvideo</xilinx:tag>
        <xilinx:tag xilinx:name="ui.data.coregen.df@34a205d6_ARCHIVE_LOCATION">v:/zxnext/zxvideo</xilinx:tag>
        <xilinx:tag xilinx:name="ui.data.coregen.df@6887909f_ARCHIVE_LOCATION">v:/zxnext/zxvideo</xilinx:tag>
        <xilinx:tag xilinx:name="ui.data.coregen.df@3c96cf42_ARCHIVE_LOCATION">v:/zxnext/zxvideo</xilinx:tag>
        <xilinx:tag xilinx:name="ui.data.coregen.df@a78c188_ARCHIVE_LOCATION">v:/zxnext/zxvideo</xilinx:tag>
        <xilinx:tag xilinx:name="ui.data.coregen.df@75f4cf04_ARCHIVE_LOCATION">v:/zxnext/zxvideo</xilinx:tag>
        <xilinx:tag xilinx:name="ui.data.coregen.df@1bc38aee_ARCHIVE_LOCATION">v:/zxnext/zxvideo</xilinx:tag>
        <xilinx:tag xilinx:name="ui.data.coregen.df@4d0ca9ab_ARCHIVE_LOCATION">v:/zxnext/zxvideo</xilinx:tag>
        <xilinx:tag xilinx:name="ui.data.coregen.df@1a2524ef_ARCHIVE_LOCATION">v:/zxnext/zxvideo</xilinx:tag>
        <xilinx:tag xilinx:name="ui.data.coregen.df@234cad8e_ARCHIVE_LOCATION">v:/zxnext/zxvideo</xilinx:tag>
        <xilinx:tag xilinx:name="ui.data.coregen.df@7fa64e6b_ARCHIVE_LOCATION">v:/zxnext/zxvideo</xilinx:tag>
        <xilinx:tag xilinx:name="ui.data.coregen.df@4b846c3_ARCHIVE_LOCATION">v:/zxnext/zxvideo</xilinx:tag>
        <xilinx:tag xilinx:name="ui.data.coregen.df@783e8867_ARCHIVE_LOCATION">v:/zxnext/zxvideo</xilinx:tag>
        <xilinx:tag xilinx:name="ui.data.coregen.df@3d2e230b_ARCHIVE_LOCATION">v:/zxnext/zxvideo</xilinx:tag>
        <xilinx:tag xilinx:name="ui.data.coregen.df@3447f894_ARCHIVE_LOCATION">v:/zxnext/zxvideo</xilinx:tag>
        <xilinx:tag xilinx:name="ui.data.coregen.df@42cbbb87_ARCHIVE_LOCATION">v:/zxnext/zxvideo</xilinx:tag>
        <xilinx:tag xilinx:name="ui.data.coregen.df@7c2a0336_ARCHIVE_LOCATION">v:/zxnext/zxvideo</xilinx:tag>
        <xilinx:tag xilinx:name="ui.data.coregen.df@52a8a5be_ARCHIVE_LOCATION">v:/zxnext/zxvideo</xilinx:tag>
        <xilinx:tag xilinx:name="ui.data.coregen.df@4b39400_ARCHIVE_LOCATION">v:/zxnext/zxvideo</xilinx:tag>
        <xilinx:tag xilinx:name="ui.data.coregen.df@1c71cbc3_ARCHIVE_LOCATION">v:/zxnext/zxvideo</xilinx:tag>
        <xilinx:tag xilinx:name="ui.data.coregen.df@125912e2_ARCHIVE_LOCATION">v:/zxnext/zxvideo</xilinx:tag>
        <xilinx:tag xilinx:name="ui.data.coregen.df@56f8a79a_ARCHIVE_LOCATION">v:/zxnext/zxvideo</xilinx:tag>
        <xilinx:tag xilinx:name="ui.data.coregen.df@51f86ad8_ARCHIVE_LOCATION">v:/zxnext/zxvideo</xilinx:tag>
        <xilinx:tag xilinx:name="ui.data.coregen.df@78572cae_ARCHIVE_LOCATION">v:/zxnext/zxvideo</xilinx:tag>
        <xilinx:tag xilinx:name="ui.data.coregen.df@61170070_ARCHIVE_LOCATION">v:/zxnext/zxvideo</xilinx:tag>
        <xilinx:tag xilinx:name="ui.data.coregen.df@2ec78669_ARCHIVE_LOCATION">v:/zxnext/zxvideo</xilinx:tag>
        <xilinx:tag xilinx:name="ui.data.coregen.df@4ea227e3_ARCHIVE_LOCATION">v:/zxnext/zxvideo</xilinx:tag>
        <xilinx:tag xilinx:name="ui.data.coregen.df@614058b2_ARCHIVE_LOCATION">v:/zxnext/zxvideo</xilinx:tag>
        <xilinx:tag xilinx:name="ui.data.coregen.df@6cf56faf_ARCHIVE_LOCATION">v:/zxnext/zxvideo</xilinx:tag>
        <xilinx:tag xilinx:name="ui.data.coregen.df@1b2a78a_ARCHIVE_LOCATION">v:/zxnext/zxvideo</xilinx:tag>
        <xilinx:tag xilinx:name="ui.data.coregen.df@3e03b445_ARCHIVE_LOCATION">v:/zxnext/zxvideo</xilinx:tag>
        <xilinx:tag xilinx:name="ui.data.coregen.df@a4e4071_ARCHIVE_LOCATION">v:/zxnext/zxvideo</xilinx:tag>
        <xilinx:tag xilinx:name="ui.data.coregen.df@76af4295_ARCHIVE_LOCATION">v:/zxnext/zxvideo</xilinx:tag>
        <xilinx:tag xilinx:name="ui.data.coregen.df@6c8473e2_ARCHIVE_LOCATION">v:/zxnext/zxvideo</xilinx:tag>
        <xilinx:tag xilinx:name="ui.data.coregen.df@3c456386_ARCHIVE_LOCATION">v:/zxnext/zxvideo</xilinx:tag>
        <xilinx:tag xilinx:name="ui.data.coregen.df@7ccb6aa0_ARCHIVE_LOCATION">v:/zxnext/zxvideo</xilinx:tag>
        <xilinx:tag xilinx:name="ui.data.coregen.df@15b0b1ab_ARCHIVE_LOCATION">v:/zxnext/zxvideo</xilinx:tag>
        <xilinx:tag xilinx:name="ui.data.coregen.df@973a7bf_ARCHIVE_LOCATION">v:/zxnext/zxvideo</xilinx:tag>
        <xilinx:tag xilinx:name="ui.data.coregen.df@24972a68_ARCHIVE_LOCATION">v:/zxnext/zxvideo</xilinx:tag>
        <xilinx:tag xilinx:name="ui.data.coregen.df@7d09bda1_ARCHIVE_LOCATION">v:/zxnext/zxvideo</xilinx:tag>
        <xilinx:tag xilinx:name="ui.data.coregen.df@5a74918b_ARCHIVE_LOCATION">v:/zxnext/zxvideo</xilinx:tag>
        <xilinx:tag xilinx:name="ui.data.coregen.df@33756455_ARCHIVE_LOCATION">v:/zxnext/zxvideo</xilinx:tag>
        <xilinx:tag xilinx:name="ui.data.coregen.df@270118d1_ARCHIVE_LOCATION">v:/zxnext/zxvideo</xilinx:tag>
        <xilinx:tag xilinx:name="ui.data.coregen.df@40da603_ARCHIVE_LOCATION">v:/zxnext/zxvideo</xilinx:tag>
        <xilinx:tag xilinx:name="ui.data.coregen.df@135c3754_ARCHIVE_LOCATION">v:/zxnext/zxvideo</xilinx:tag>
        <xilinx:tag xilinx:name="ui.data.coregen.df@316e07d3_ARCHIVE_LOCATION">v:/zxnext/zxvideo</xilinx:tag>
        <xilinx:tag xilinx:name="ui.data.coregen.df@b8a847f_ARCHIVE_LOCATION">v:/zxnext/zxvideo</xilinx:tag>
        <xilinx:tag xilinx:name="ui.data.coregen.df@5976acee_ARCHIVE_LOCATION">v:/zxnext/zxvideo</xilinx:tag>
        <xilinx:tag xilinx:name="ui.data.coregen.df@70af4fd8_ARCHIVE_LOCATION">v:/zxnext/zxvideo</xilinx:tag>
        <xilinx:tag xilinx:name="ui.data.coregen.df@4e8363a6_ARCHIVE_LOCATION">v:/zxnext/zxvideo</xilinx:tag>
        <xilinx:tag xilinx:name="ui.data.coregen.df@144f1c62_ARCHIVE_LOCATION">v:/zxnext/zxvideo</xilinx:tag>
        <xilinx:tag xilinx:name="ui.data.coregen.df@6591b010_ARCHIVE_LOCATION">v:/zxnext/zxvideo</xilinx:tag>
        <xilinx:tag xilinx:name="ui.data.coregen.df@15a5021b_ARCHIVE_LOCATION">v:/zxnext/zxvideo</xilinx:tag>
        <xilinx:tag xilinx:name="ui.data.coregen.df@3d370d1_ARCHIVE_LOCATION">v:/zxnext/zxvideo</xilinx:tag>
        <xilinx:tag xilinx:name="ui.data.coregen.df@54859501_ARCHIVE_LOCATION">v:/zxnext/zxvideo</xilinx:tag>
        <xilinx:tag xilinx:name="ui.data.coregen.df@3c4cd775_ARCHIVE_LOCATION">v:/zxnext/zxvideo</xilinx:tag>
        <xilinx:tag xilinx:name="ui.data.coregen.df@3ee312e1_ARCHIVE_LOCATION">v:/zxnext/zxvideo</xilinx:tag>
        <xilinx:tag xilinx:name="ui.data.coregen.df@40e0e823_ARCHIVE_LOCATION">v:/zxnext/zxvideo</xilinx:tag>
        <xilinx:tag xilinx:name="ui.data.coregen.df@4b0e36bb_ARCHIVE_LOCATION">v:/zxnext/zxvideo</xilinx:tag>
        <xilinx:tag xilinx:name="ui.data.coregen.df@3e0ecc90_ARCHIVE_LOCATION">v:/zxnext/zxvideo</xilinx:tag>
        <xilinx:tag xilinx:name="ui.data.coregen.df@372d3bd6_ARCHIVE_LOCATION">v:/zxnext/zxvideo</xilinx:tag>
        <xilinx:tag xilinx:name="ui.data.coregen.df@604a06f_ARCHIVE_LOCATION">v:/zxnext/zxvideo</xilinx:tag>
        <xilinx:tag xilinx:name="ui.data.coregen.df@349cc2b4_ARCHIVE_LOCATION">v:/zxnext/zxvideo</xilinx:tag>
        <xilinx:tag xilinx:name="ui.data.coregen.df@2669659b_ARCHIVE_LOCATION">v:/zxnext/zxvideo</xilinx:tag>
        <xilinx:tag xilinx:name="ui.data.coregen.df@52b03e7f_ARCHIVE_LOCATION">v:/zxnext/zxvideo</xilinx:tag>
        <xilinx:tag xilinx:name="ui.data.coregen.df@7484527e_ARCHIVE_LOCATION">v:/zxnext/zxvideo</xilinx:tag>
        <xilinx:tag xilinx:name="ui.data.coregen.df@3e9cbf07_ARCHIVE_LOCATION">v:/zxnext/zxvideo</xilinx:tag>
        <xilinx:tag xilinx:name="ui.data.coregen.df@3cf2b97b_ARCHIVE_LOCATION">v:/zxnext/zxvideo</xilinx:tag>
        <xilinx:tag xilinx:name="ui.data.coregen.df@39d2adf0_ARCHIVE_LOCATION">v:/zxnext/zxvideo</xilinx:tag>
        <xilinx:tag xilinx:name="ui.data.coregen.df@142b27c_ARCHIVE_LOCATION">v:/zxnext/zxvideo</xilinx:tag>
        <xilinx:tag xilinx:name="ui.data.coregen.df@14d0d890_ARCHIVE_LOCATION">v:/zxnext/zxvideo</xilinx:tag>
        <xilinx:tag xilinx:name="ui.data.coregen.df@70910658_ARCHIVE_LOCATION">v:/zxnext/zxvideo</xilinx:tag>
        <xilinx:tag xilinx:name="ui.data.coregen.df@4cd84b26_ARCHIVE_LOCATION">v:/zxnext/zxvideo</xilinx:tag>
        <xilinx:tag xilinx:name="ui.data.coregen.df@2ff64827_ARCHIVE_LOCATION">v:/zxnext/zxvideo</xilinx:tag>
        <xilinx:tag xilinx:name="ui.data.coregen.df@913cbbe_ARCHIVE_LOCATION">v:/zxnext/zxvideo</xilinx:tag>
        <xilinx:tag xilinx:name="ui.data.coregen.df@287588f0_ARCHIVE_LOCATION">v:/zxnext/zxvideo</xilinx:tag>
        <xilinx:tag xilinx:name="ui.data.coregen.df@34c9aa63_ARCHIVE_LOCATION">v:/zxnext/zxvideo</xilinx:tag>
        <xilinx:tag xilinx:name="ui.data.coregen.df@5663609a_ARCHIVE_LOCATION">v:/zxnext/zxvideo</xilinx:tag>
        <xilinx:tag xilinx:name="ui.data.coregen.df@5c221a9e_ARCHIVE_LOCATION">v:/zxnext/zxvideo</xilinx:tag>
        <xilinx:tag xilinx:name="ui.data.coregen.df@563eeb24_ARCHIVE_LOCATION">v:/zxnext/zxvideo</xilinx:tag>
        <xilinx:tag xilinx:name="ui.data.coregen.df@444ba6c4_ARCHIVE_LOCATION">v:/zxnext/zxvideo</xilinx:tag>
        <xilinx:tag xilinx:name="ui.data.coregen.df@35751988_ARCHIVE_LOCATION">v:/zxnext/zxvideo</xilinx:tag>
      </xilinx:tags>
    </xilinx:coreExtensions>
    <xilinx:packagingInfo>
      <xilinx:xilinxVersion>2021.2</xilinx:xilinxVersion>
      <xilinx:checksum xilinx:scope="busInterfaces" xilinx:value="6b361a4a"/>
      <xilinx:checksum xilinx:scope="fileGroups" xilinx:value="c1041749"/>
      <xilinx:checksum xilinx:scope="ports" xilinx:value="a0af37a5"/>
      <xilinx:checksum xilinx:scope="parameters" xilinx:value="a28eeba7"/>
    </xilinx:packagingInfo>
  </spirit:vendorExtensions>
</spirit:component>
