<?xml version="1.0" encoding="UTF-8"?>
<spirit:component xmlns:xilinx="http://www.xilinx.com" xmlns:spirit="http://www.spiritconsortium.org/XMLSchema/SPIRIT/1685-2009" xmlns:xsi="http://www.w3.org/2001/XMLSchema-instance">
  <spirit:vendor>specnext.com</spirit:vendor>
  <spirit:library>customized_ip</spirit:library>
  <spirit:name>zxnexys_zxvideo_0_0</spirit:name>
  <spirit:version>1.0</spirit:version>
  <spirit:busInterfaces>
    <spirit:busInterface>
      <spirit:name>video</spirit:name>
      <spirit:busType spirit:vendor="specnext.com" spirit:library="specnext" spirit:name="video" spirit:version="1.0"/>
      <spirit:abstractionType spirit:vendor="specnext.com" spirit:library="specnext" spirit:name="video_rtl" spirit:version="1.0"/>
      <spirit:slave/>
      <spirit:portMaps>
        <spirit:portMap>
          <spirit:logicalPort>
            <spirit:name>rgb</spirit:name>
          </spirit:logicalPort>
          <spirit:physicalPort>
            <spirit:name>rgb</spirit:name>
          </spirit:physicalPort>
        </spirit:portMap>
        <spirit:portMap>
          <spirit:logicalPort>
            <spirit:name>csync_n</spirit:name>
          </spirit:logicalPort>
          <spirit:physicalPort>
            <spirit:name>csync_n</spirit:name>
          </spirit:physicalPort>
        </spirit:portMap>
        <spirit:portMap>
          <spirit:logicalPort>
            <spirit:name>vsync_n</spirit:name>
          </spirit:logicalPort>
          <spirit:physicalPort>
            <spirit:name>vsync_n</spirit:name>
          </spirit:physicalPort>
        </spirit:portMap>
        <spirit:portMap>
          <spirit:logicalPort>
            <spirit:name>hsync_n</spirit:name>
          </spirit:logicalPort>
          <spirit:physicalPort>
            <spirit:name>hsync_n</spirit:name>
          </spirit:physicalPort>
        </spirit:portMap>
        <spirit:portMap>
          <spirit:logicalPort>
            <spirit:name>scanlines</spirit:name>
          </spirit:logicalPort>
          <spirit:physicalPort>
            <spirit:name>scanlines</spirit:name>
          </spirit:physicalPort>
        </spirit:portMap>
        <spirit:portMap>
          <spirit:logicalPort>
            <spirit:name>scandouble</spirit:name>
          </spirit:logicalPort>
          <spirit:physicalPort>
            <spirit:name>scandouble</spirit:name>
          </spirit:physicalPort>
        </spirit:portMap>
        <spirit:portMap>
          <spirit:logicalPort>
            <spirit:name>machine_timing</spirit:name>
          </spirit:logicalPort>
          <spirit:physicalPort>
            <spirit:name>machine_timing</spirit:name>
          </spirit:physicalPort>
        </spirit:portMap>
      </spirit:portMaps>
    </spirit:busInterface>
    <spirit:busInterface>
      <spirit:name>clk_peripheral</spirit:name>
      <spirit:busType spirit:vendor="xilinx.com" spirit:library="signal" spirit:name="clock" spirit:version="1.0"/>
      <spirit:abstractionType spirit:vendor="xilinx.com" spirit:library="signal" spirit:name="clock_rtl" spirit:version="1.0"/>
      <spirit:slave/>
      <spirit:portMaps>
        <spirit:portMap>
          <spirit:logicalPort>
            <spirit:name>CLK</spirit:name>
          </spirit:logicalPort>
          <spirit:physicalPort>
            <spirit:name>clk_peripheral</spirit:name>
          </spirit:physicalPort>
        </spirit:portMap>
      </spirit:portMaps>
      <spirit:parameters>
        <spirit:parameter>
          <spirit:name>ASSOCIATED_BUSIF</spirit:name>
          <spirit:value spirit:id="BUSIFPARAM_VALUE.CLK_PERIPHERAL.ASSOCIATED_BUSIF">specnext_video:video</spirit:value>
        </spirit:parameter>
        <spirit:parameter>
          <spirit:name>FREQ_HZ</spirit:name>
          <spirit:value spirit:format="long" spirit:resolve="generated" spirit:id="BUSIFPARAM_VALUE.CLK_PERIPHERAL.FREQ_HZ">100000000</spirit:value>
          <spirit:vendorExtensions>
            <xilinx:parameterInfo>
              <xilinx:parameterUsage>none</xilinx:parameterUsage>
            </xilinx:parameterInfo>
          </spirit:vendorExtensions>
        </spirit:parameter>
        <spirit:parameter>
          <spirit:name>FREQ_TOLERANCE_HZ</spirit:name>
          <spirit:value spirit:format="long" spirit:resolve="generated" spirit:id="BUSIFPARAM_VALUE.CLK_PERIPHERAL.FREQ_TOLERANCE_HZ">0</spirit:value>
          <spirit:vendorExtensions>
            <xilinx:parameterInfo>
              <xilinx:parameterUsage>none</xilinx:parameterUsage>
            </xilinx:parameterInfo>
          </spirit:vendorExtensions>
        </spirit:parameter>
        <spirit:parameter>
          <spirit:name>PHASE</spirit:name>
          <spirit:value spirit:format="float" spirit:resolve="generated" spirit:id="BUSIFPARAM_VALUE.CLK_PERIPHERAL.PHASE">0.0</spirit:value>
          <spirit:vendorExtensions>
            <xilinx:parameterInfo>
              <xilinx:parameterUsage>none</xilinx:parameterUsage>
            </xilinx:parameterInfo>
          </spirit:vendorExtensions>
        </spirit:parameter>
        <spirit:parameter>
          <spirit:name>CLK_DOMAIN</spirit:name>
          <spirit:value spirit:resolve="generated" spirit:id="BUSIFPARAM_VALUE.CLK_PERIPHERAL.CLK_DOMAIN">zxnexys_zxclock_0_0_clk_peripheral</spirit:value>
          <spirit:vendorExtensions>
            <xilinx:parameterInfo>
              <xilinx:parameterUsage>none</xilinx:parameterUsage>
            </xilinx:parameterInfo>
          </spirit:vendorExtensions>
        </spirit:parameter>
        <spirit:parameter>
          <spirit:name>ASSOCIATED_PORT</spirit:name>
          <spirit:value spirit:resolve="generated" spirit:id="BUSIFPARAM_VALUE.CLK_PERIPHERAL.ASSOCIATED_PORT"/>
          <spirit:vendorExtensions>
            <xilinx:parameterInfo>
              <xilinx:parameterUsage>none</xilinx:parameterUsage>
            </xilinx:parameterInfo>
          </spirit:vendorExtensions>
        </spirit:parameter>
        <spirit:parameter>
          <spirit:name>ASSOCIATED_RESET</spirit:name>
          <spirit:value spirit:resolve="generated" spirit:id="BUSIFPARAM_VALUE.CLK_PERIPHERAL.ASSOCIATED_RESET"/>
          <spirit:vendorExtensions>
            <xilinx:parameterInfo>
              <xilinx:parameterUsage>none</xilinx:parameterUsage>
            </xilinx:parameterInfo>
          </spirit:vendorExtensions>
        </spirit:parameter>
        <spirit:parameter>
          <spirit:name>INSERT_VIP</spirit:name>
          <spirit:value spirit:format="long" spirit:resolve="user" spirit:id="BUSIFPARAM_VALUE.CLK_PERIPHERAL.INSERT_VIP">0</spirit:value>
          <spirit:vendorExtensions>
            <xilinx:parameterInfo>
              <xilinx:parameterUsage>simulation.rtl</xilinx:parameterUsage>
            </xilinx:parameterInfo>
          </spirit:vendorExtensions>
        </spirit:parameter>
      </spirit:parameters>
    </spirit:busInterface>
    <spirit:busInterface>
      <spirit:name>clk_peripheral_n</spirit:name>
      <spirit:busType spirit:vendor="xilinx.com" spirit:library="signal" spirit:name="clock" spirit:version="1.0"/>
      <spirit:abstractionType spirit:vendor="xilinx.com" spirit:library="signal" spirit:name="clock_rtl" spirit:version="1.0"/>
      <spirit:slave/>
      <spirit:portMaps>
        <spirit:portMap>
          <spirit:logicalPort>
            <spirit:name>CLK</spirit:name>
          </spirit:logicalPort>
          <spirit:physicalPort>
            <spirit:name>clk_peripheral_n</spirit:name>
          </spirit:physicalPort>
        </spirit:portMap>
      </spirit:portMaps>
      <spirit:parameters>
        <spirit:parameter>
          <spirit:name>FREQ_HZ</spirit:name>
          <spirit:value spirit:format="long" spirit:resolve="generated" spirit:id="BUSIFPARAM_VALUE.CLK_PERIPHERAL_N.FREQ_HZ">100000000</spirit:value>
          <spirit:vendorExtensions>
            <xilinx:parameterInfo>
              <xilinx:parameterUsage>none</xilinx:parameterUsage>
            </xilinx:parameterInfo>
          </spirit:vendorExtensions>
        </spirit:parameter>
        <spirit:parameter>
          <spirit:name>FREQ_TOLERANCE_HZ</spirit:name>
          <spirit:value spirit:format="long" spirit:resolve="generated" spirit:id="BUSIFPARAM_VALUE.CLK_PERIPHERAL_N.FREQ_TOLERANCE_HZ">0</spirit:value>
          <spirit:vendorExtensions>
            <xilinx:parameterInfo>
              <xilinx:parameterUsage>none</xilinx:parameterUsage>
            </xilinx:parameterInfo>
          </spirit:vendorExtensions>
        </spirit:parameter>
        <spirit:parameter>
          <spirit:name>PHASE</spirit:name>
          <spirit:value spirit:format="float" spirit:resolve="generated" spirit:id="BUSIFPARAM_VALUE.CLK_PERIPHERAL_N.PHASE">0.0</spirit:value>
          <spirit:vendorExtensions>
            <xilinx:parameterInfo>
              <xilinx:parameterUsage>none</xilinx:parameterUsage>
            </xilinx:parameterInfo>
          </spirit:vendorExtensions>
        </spirit:parameter>
        <spirit:parameter>
          <spirit:name>CLK_DOMAIN</spirit:name>
          <spirit:value spirit:resolve="generated" spirit:id="BUSIFPARAM_VALUE.CLK_PERIPHERAL_N.CLK_DOMAIN">zxnexys_zxclock_0_0_clk_peripheral_n</spirit:value>
          <spirit:vendorExtensions>
            <xilinx:parameterInfo>
              <xilinx:parameterUsage>none</xilinx:parameterUsage>
            </xilinx:parameterInfo>
          </spirit:vendorExtensions>
        </spirit:parameter>
        <spirit:parameter>
          <spirit:name>ASSOCIATED_BUSIF</spirit:name>
          <spirit:value spirit:resolve="generated" spirit:id="BUSIFPARAM_VALUE.CLK_PERIPHERAL_N.ASSOCIATED_BUSIF"/>
          <spirit:vendorExtensions>
            <xilinx:parameterInfo>
              <xilinx:parameterUsage>none</xilinx:parameterUsage>
            </xilinx:parameterInfo>
          </spirit:vendorExtensions>
        </spirit:parameter>
        <spirit:parameter>
          <spirit:name>ASSOCIATED_PORT</spirit:name>
          <spirit:value spirit:resolve="generated" spirit:id="BUSIFPARAM_VALUE.CLK_PERIPHERAL_N.ASSOCIATED_PORT"/>
          <spirit:vendorExtensions>
            <xilinx:parameterInfo>
              <xilinx:parameterUsage>none</xilinx:parameterUsage>
            </xilinx:parameterInfo>
          </spirit:vendorExtensions>
        </spirit:parameter>
        <spirit:parameter>
          <spirit:name>ASSOCIATED_RESET</spirit:name>
          <spirit:value spirit:resolve="generated" spirit:id="BUSIFPARAM_VALUE.CLK_PERIPHERAL_N.ASSOCIATED_RESET"/>
          <spirit:vendorExtensions>
            <xilinx:parameterInfo>
              <xilinx:parameterUsage>none</xilinx:parameterUsage>
            </xilinx:parameterInfo>
          </spirit:vendorExtensions>
        </spirit:parameter>
        <spirit:parameter>
          <spirit:name>INSERT_VIP</spirit:name>
          <spirit:value spirit:format="long" spirit:resolve="user" spirit:id="BUSIFPARAM_VALUE.CLK_PERIPHERAL_N.INSERT_VIP">0</spirit:value>
          <spirit:vendorExtensions>
            <xilinx:parameterInfo>
              <xilinx:parameterUsage>simulation.rtl</xilinx:parameterUsage>
            </xilinx:parameterInfo>
          </spirit:vendorExtensions>
        </spirit:parameter>
      </spirit:parameters>
    </spirit:busInterface>
    <spirit:busInterface>
      <spirit:name>clk_video</spirit:name>
      <spirit:busType spirit:vendor="xilinx.com" spirit:library="signal" spirit:name="clock" spirit:version="1.0"/>
      <spirit:abstractionType spirit:vendor="xilinx.com" spirit:library="signal" spirit:name="clock_rtl" spirit:version="1.0"/>
      <spirit:slave/>
      <spirit:portMaps>
        <spirit:portMap>
          <spirit:logicalPort>
            <spirit:name>CLK</spirit:name>
          </spirit:logicalPort>
          <spirit:physicalPort>
            <spirit:name>clk_video</spirit:name>
          </spirit:physicalPort>
        </spirit:portMap>
      </spirit:portMaps>
      <spirit:parameters>
        <spirit:parameter>
          <spirit:name>FREQ_HZ</spirit:name>
          <spirit:value spirit:format="long" spirit:resolve="generated" spirit:id="BUSIFPARAM_VALUE.CLK_VIDEO.FREQ_HZ">100000000</spirit:value>
          <spirit:vendorExtensions>
            <xilinx:parameterInfo>
              <xilinx:parameterUsage>none</xilinx:parameterUsage>
            </xilinx:parameterInfo>
          </spirit:vendorExtensions>
        </spirit:parameter>
        <spirit:parameter>
          <spirit:name>FREQ_TOLERANCE_HZ</spirit:name>
          <spirit:value spirit:format="long" spirit:resolve="generated" spirit:id="BUSIFPARAM_VALUE.CLK_VIDEO.FREQ_TOLERANCE_HZ">0</spirit:value>
          <spirit:vendorExtensions>
            <xilinx:parameterInfo>
              <xilinx:parameterUsage>none</xilinx:parameterUsage>
            </xilinx:parameterInfo>
          </spirit:vendorExtensions>
        </spirit:parameter>
        <spirit:parameter>
          <spirit:name>PHASE</spirit:name>
          <spirit:value spirit:format="float" spirit:resolve="generated" spirit:id="BUSIFPARAM_VALUE.CLK_VIDEO.PHASE">0.0</spirit:value>
          <spirit:vendorExtensions>
            <xilinx:parameterInfo>
              <xilinx:parameterUsage>none</xilinx:parameterUsage>
            </xilinx:parameterInfo>
          </spirit:vendorExtensions>
        </spirit:parameter>
        <spirit:parameter>
          <spirit:name>CLK_DOMAIN</spirit:name>
          <spirit:value spirit:resolve="generated" spirit:id="BUSIFPARAM_VALUE.CLK_VIDEO.CLK_DOMAIN">zxnexys_zxclock_0_0_clk_video</spirit:value>
          <spirit:vendorExtensions>
            <xilinx:parameterInfo>
              <xilinx:parameterUsage>none</xilinx:parameterUsage>
            </xilinx:parameterInfo>
          </spirit:vendorExtensions>
        </spirit:parameter>
        <spirit:parameter>
          <spirit:name>ASSOCIATED_BUSIF</spirit:name>
          <spirit:value spirit:resolve="generated" spirit:id="BUSIFPARAM_VALUE.CLK_VIDEO.ASSOCIATED_BUSIF"/>
          <spirit:vendorExtensions>
            <xilinx:parameterInfo>
              <xilinx:parameterUsage>none</xilinx:parameterUsage>
            </xilinx:parameterInfo>
          </spirit:vendorExtensions>
        </spirit:parameter>
        <spirit:parameter>
          <spirit:name>ASSOCIATED_PORT</spirit:name>
          <spirit:value spirit:resolve="generated" spirit:id="BUSIFPARAM_VALUE.CLK_VIDEO.ASSOCIATED_PORT"/>
          <spirit:vendorExtensions>
            <xilinx:parameterInfo>
              <xilinx:parameterUsage>none</xilinx:parameterUsage>
            </xilinx:parameterInfo>
          </spirit:vendorExtensions>
        </spirit:parameter>
        <spirit:parameter>
          <spirit:name>ASSOCIATED_RESET</spirit:name>
          <spirit:value spirit:resolve="generated" spirit:id="BUSIFPARAM_VALUE.CLK_VIDEO.ASSOCIATED_RESET"/>
          <spirit:vendorExtensions>
            <xilinx:parameterInfo>
              <xilinx:parameterUsage>none</xilinx:parameterUsage>
            </xilinx:parameterInfo>
          </spirit:vendorExtensions>
        </spirit:parameter>
        <spirit:parameter>
          <spirit:name>INSERT_VIP</spirit:name>
          <spirit:value spirit:format="long" spirit:resolve="user" spirit:id="BUSIFPARAM_VALUE.CLK_VIDEO.INSERT_VIP">0</spirit:value>
          <spirit:vendorExtensions>
            <xilinx:parameterInfo>
              <xilinx:parameterUsage>simulation.rtl</xilinx:parameterUsage>
            </xilinx:parameterInfo>
          </spirit:vendorExtensions>
        </spirit:parameter>
      </spirit:parameters>
    </spirit:busInterface>
  </spirit:busInterfaces>
  <spirit:model>
    <spirit:views>
      <spirit:view>
        <spirit:name>xilinx_anylanguagesynthesis</spirit:name>
        <spirit:displayName>Synthesis</spirit:displayName>
        <spirit:envIdentifier>:vivado.xilinx.com:synthesis</spirit:envIdentifier>
        <spirit:modelName>zxvideo_wrapper</spirit:modelName>
        <spirit:fileSetRef>
          <spirit:localName>xilinx_anylanguagesynthesis_view_fileset</spirit:localName>
        </spirit:fileSetRef>
        <spirit:parameters>
          <spirit:parameter>
            <spirit:name>GENtimestamp</spirit:name>
            <spirit:value>Sun Dec 12 00:55:23 UTC 2021</spirit:value>
          </spirit:parameter>
          <spirit:parameter>
            <spirit:name>outputProductCRC</spirit:name>
            <spirit:value>9:786b8edb</spirit:value>
          </spirit:parameter>
        </spirit:parameters>
      </spirit:view>
      <spirit:view>
        <spirit:name>xilinx_synthesisconstraints</spirit:name>
        <spirit:displayName>Synthesis Constraints</spirit:displayName>
        <spirit:envIdentifier>:vivado.xilinx.com:synthesis.constraints</spirit:envIdentifier>
        <spirit:parameters>
          <spirit:parameter>
            <spirit:name>outputProductCRC</spirit:name>
            <spirit:value>9:786b8edb</spirit:value>
          </spirit:parameter>
        </spirit:parameters>
      </spirit:view>
      <spirit:view>
        <spirit:name>xilinx_verilogsynthesiswrapper</spirit:name>
        <spirit:displayName>Verilog Synthesis Wrapper</spirit:displayName>
        <spirit:envIdentifier>verilogSource:vivado.xilinx.com:synthesis.wrapper</spirit:envIdentifier>
        <spirit:language>verilog</spirit:language>
        <spirit:modelName>zxnexys_zxvideo_0_0</spirit:modelName>
        <spirit:fileSetRef>
          <spirit:localName>xilinx_verilogsynthesiswrapper_view_fileset</spirit:localName>
        </spirit:fileSetRef>
        <spirit:parameters>
          <spirit:parameter>
            <spirit:name>GENtimestamp</spirit:name>
            <spirit:value>Sun Dec 12 00:55:23 UTC 2021</spirit:value>
          </spirit:parameter>
          <spirit:parameter>
            <spirit:name>outputProductCRC</spirit:name>
            <spirit:value>9:786b8edb</spirit:value>
          </spirit:parameter>
        </spirit:parameters>
      </spirit:view>
      <spirit:view>
        <spirit:name>xilinx_anylanguagebehavioralsimulation</spirit:name>
        <spirit:displayName>Simulation</spirit:displayName>
        <spirit:envIdentifier>:vivado.xilinx.com:simulation</spirit:envIdentifier>
        <spirit:modelName>zxvideo_wrapper</spirit:modelName>
        <spirit:fileSetRef>
          <spirit:localName>xilinx_anylanguagebehavioralsimulation_view_fileset</spirit:localName>
        </spirit:fileSetRef>
        <spirit:parameters>
          <spirit:parameter>
            <spirit:name>GENtimestamp</spirit:name>
            <spirit:value>Sun Dec 12 00:55:23 UTC 2021</spirit:value>
          </spirit:parameter>
          <spirit:parameter>
            <spirit:name>outputProductCRC</spirit:name>
            <spirit:value>9:fbc6aee8</spirit:value>
          </spirit:parameter>
        </spirit:parameters>
      </spirit:view>
      <spirit:view>
        <spirit:name>xilinx_verilogsimulationwrapper</spirit:name>
        <spirit:displayName>Verilog Simulation Wrapper</spirit:displayName>
        <spirit:envIdentifier>verilogSource:vivado.xilinx.com:simulation.wrapper</spirit:envIdentifier>
        <spirit:language>verilog</spirit:language>
        <spirit:modelName>zxnexys_zxvideo_0_0</spirit:modelName>
        <spirit:fileSetRef>
          <spirit:localName>xilinx_verilogsimulationwrapper_view_fileset</spirit:localName>
        </spirit:fileSetRef>
        <spirit:parameters>
          <spirit:parameter>
            <spirit:name>GENtimestamp</spirit:name>
            <spirit:value>Sun Dec 12 00:55:23 UTC 2021</spirit:value>
          </spirit:parameter>
          <spirit:parameter>
            <spirit:name>outputProductCRC</spirit:name>
            <spirit:value>9:fbc6aee8</spirit:value>
          </spirit:parameter>
        </spirit:parameters>
      </spirit:view>
      <spirit:view>
        <spirit:name>xilinx_externalfiles</spirit:name>
        <spirit:displayName>External Files</spirit:displayName>
        <spirit:envIdentifier>:vivado.xilinx.com:external.files</spirit:envIdentifier>
        <spirit:fileSetRef>
          <spirit:localName>xilinx_externalfiles_view_fileset</spirit:localName>
        </spirit:fileSetRef>
        <spirit:parameters>
          <spirit:parameter>
            <spirit:name>GENtimestamp</spirit:name>
            <spirit:value>Sun Dec 12 00:56:17 UTC 2021</spirit:value>
          </spirit:parameter>
          <spirit:parameter>
            <spirit:name>outputProductCRC</spirit:name>
            <spirit:value>9:786b8edb</spirit:value>
          </spirit:parameter>
        </spirit:parameters>
      </spirit:view>
    </spirit:views>
    <spirit:ports>
      <spirit:port>
        <spirit:name>b</spirit:name>
        <spirit:wire>
          <spirit:direction>out</spirit:direction>
          <spirit:vector>
            <spirit:left spirit:format="long">3</spirit:left>
            <spirit:right spirit:format="long">0</spirit:right>
          </spirit:vector>
          <spirit:wireTypeDefs>
            <spirit:wireTypeDef>
              <spirit:typeName>wire</spirit:typeName>
              <spirit:viewNameRef>xilinx_anylanguagesynthesis</spirit:viewNameRef>
              <spirit:viewNameRef>xilinx_anylanguagebehavioralsimulation</spirit:viewNameRef>
            </spirit:wireTypeDef>
          </spirit:wireTypeDefs>
        </spirit:wire>
      </spirit:port>
      <spirit:port>
        <spirit:name>clk_peripheral</spirit:name>
        <spirit:wire>
          <spirit:direction>in</spirit:direction>
          <spirit:wireTypeDefs>
            <spirit:wireTypeDef>
              <spirit:typeName>wire</spirit:typeName>
              <spirit:viewNameRef>xilinx_anylanguagesynthesis</spirit:viewNameRef>
              <spirit:viewNameRef>xilinx_anylanguagebehavioralsimulation</spirit:viewNameRef>
            </spirit:wireTypeDef>
          </spirit:wireTypeDefs>
        </spirit:wire>
      </spirit:port>
      <spirit:port>
        <spirit:name>clk_peripheral_n</spirit:name>
        <spirit:wire>
          <spirit:direction>in</spirit:direction>
          <spirit:wireTypeDefs>
            <spirit:wireTypeDef>
              <spirit:typeName>wire</spirit:typeName>
              <spirit:viewNameRef>xilinx_anylanguagesynthesis</spirit:viewNameRef>
              <spirit:viewNameRef>xilinx_anylanguagebehavioralsimulation</spirit:viewNameRef>
            </spirit:wireTypeDef>
          </spirit:wireTypeDefs>
        </spirit:wire>
      </spirit:port>
      <spirit:port>
        <spirit:name>clk_video</spirit:name>
        <spirit:wire>
          <spirit:direction>in</spirit:direction>
          <spirit:wireTypeDefs>
            <spirit:wireTypeDef>
              <spirit:typeName>wire</spirit:typeName>
              <spirit:viewNameRef>xilinx_anylanguagesynthesis</spirit:viewNameRef>
              <spirit:viewNameRef>xilinx_anylanguagebehavioralsimulation</spirit:viewNameRef>
            </spirit:wireTypeDef>
          </spirit:wireTypeDefs>
        </spirit:wire>
      </spirit:port>
      <spirit:port>
        <spirit:name>csync_n</spirit:name>
        <spirit:wire>
          <spirit:direction>in</spirit:direction>
          <spirit:wireTypeDefs>
            <spirit:wireTypeDef>
              <spirit:typeName>wire</spirit:typeName>
              <spirit:viewNameRef>xilinx_anylanguagesynthesis</spirit:viewNameRef>
              <spirit:viewNameRef>xilinx_anylanguagebehavioralsimulation</spirit:viewNameRef>
            </spirit:wireTypeDef>
          </spirit:wireTypeDefs>
          <spirit:driver>
            <spirit:defaultValue spirit:format="long">1</spirit:defaultValue>
          </spirit:driver>
        </spirit:wire>
      </spirit:port>
      <spirit:port>
        <spirit:name>g</spirit:name>
        <spirit:wire>
          <spirit:direction>out</spirit:direction>
          <spirit:vector>
            <spirit:left spirit:format="long">3</spirit:left>
            <spirit:right spirit:format="long">0</spirit:right>
          </spirit:vector>
          <spirit:wireTypeDefs>
            <spirit:wireTypeDef>
              <spirit:typeName>wire</spirit:typeName>
              <spirit:viewNameRef>xilinx_anylanguagesynthesis</spirit:viewNameRef>
              <spirit:viewNameRef>xilinx_anylanguagebehavioralsimulation</spirit:viewNameRef>
            </spirit:wireTypeDef>
          </spirit:wireTypeDefs>
        </spirit:wire>
      </spirit:port>
      <spirit:port>
        <spirit:name>hs</spirit:name>
        <spirit:wire>
          <spirit:direction>out</spirit:direction>
          <spirit:wireTypeDefs>
            <spirit:wireTypeDef>
              <spirit:typeName>wire</spirit:typeName>
              <spirit:viewNameRef>xilinx_anylanguagesynthesis</spirit:viewNameRef>
              <spirit:viewNameRef>xilinx_anylanguagebehavioralsimulation</spirit:viewNameRef>
            </spirit:wireTypeDef>
          </spirit:wireTypeDefs>
        </spirit:wire>
      </spirit:port>
      <spirit:port>
        <spirit:name>hsync_n</spirit:name>
        <spirit:wire>
          <spirit:direction>in</spirit:direction>
          <spirit:wireTypeDefs>
            <spirit:wireTypeDef>
              <spirit:typeName>wire</spirit:typeName>
              <spirit:viewNameRef>xilinx_anylanguagesynthesis</spirit:viewNameRef>
              <spirit:viewNameRef>xilinx_anylanguagebehavioralsimulation</spirit:viewNameRef>
            </spirit:wireTypeDef>
          </spirit:wireTypeDefs>
          <spirit:driver>
            <spirit:defaultValue spirit:format="long">1</spirit:defaultValue>
          </spirit:driver>
        </spirit:wire>
      </spirit:port>
      <spirit:port>
        <spirit:name>machine_timing</spirit:name>
        <spirit:wire>
          <spirit:direction>in</spirit:direction>
          <spirit:vector>
            <spirit:left spirit:format="long">2</spirit:left>
            <spirit:right spirit:format="long">0</spirit:right>
          </spirit:vector>
          <spirit:wireTypeDefs>
            <spirit:wireTypeDef>
              <spirit:typeName>wire</spirit:typeName>
              <spirit:viewNameRef>xilinx_anylanguagesynthesis</spirit:viewNameRef>
              <spirit:viewNameRef>xilinx_anylanguagebehavioralsimulation</spirit:viewNameRef>
            </spirit:wireTypeDef>
          </spirit:wireTypeDefs>
          <spirit:driver>
            <spirit:defaultValue spirit:format="long">0</spirit:defaultValue>
          </spirit:driver>
        </spirit:wire>
      </spirit:port>
      <spirit:port>
        <spirit:name>r</spirit:name>
        <spirit:wire>
          <spirit:direction>out</spirit:direction>
          <spirit:vector>
            <spirit:left spirit:format="long">3</spirit:left>
            <spirit:right spirit:format="long">0</spirit:right>
          </spirit:vector>
          <spirit:wireTypeDefs>
            <spirit:wireTypeDef>
              <spirit:typeName>wire</spirit:typeName>
              <spirit:viewNameRef>xilinx_anylanguagesynthesis</spirit:viewNameRef>
              <spirit:viewNameRef>xilinx_anylanguagebehavioralsimulation</spirit:viewNameRef>
            </spirit:wireTypeDef>
          </spirit:wireTypeDefs>
        </spirit:wire>
      </spirit:port>
      <spirit:port>
        <spirit:name>rgb</spirit:name>
        <spirit:wire>
          <spirit:direction>in</spirit:direction>
          <spirit:vector>
            <spirit:left spirit:format="long">8</spirit:left>
            <spirit:right spirit:format="long">0</spirit:right>
          </spirit:vector>
          <spirit:wireTypeDefs>
            <spirit:wireTypeDef>
              <spirit:typeName>wire</spirit:typeName>
              <spirit:viewNameRef>xilinx_anylanguagesynthesis</spirit:viewNameRef>
              <spirit:viewNameRef>xilinx_anylanguagebehavioralsimulation</spirit:viewNameRef>
            </spirit:wireTypeDef>
          </spirit:wireTypeDefs>
          <spirit:driver>
            <spirit:defaultValue spirit:format="long">0</spirit:defaultValue>
          </spirit:driver>
        </spirit:wire>
      </spirit:port>
      <spirit:port>
        <spirit:name>scandouble</spirit:name>
        <spirit:wire>
          <spirit:direction>in</spirit:direction>
          <spirit:wireTypeDefs>
            <spirit:wireTypeDef>
              <spirit:typeName>wire</spirit:typeName>
              <spirit:viewNameRef>xilinx_anylanguagesynthesis</spirit:viewNameRef>
              <spirit:viewNameRef>xilinx_anylanguagebehavioralsimulation</spirit:viewNameRef>
            </spirit:wireTypeDef>
          </spirit:wireTypeDefs>
          <spirit:driver>
            <spirit:defaultValue spirit:format="long">0</spirit:defaultValue>
          </spirit:driver>
        </spirit:wire>
      </spirit:port>
      <spirit:port>
        <spirit:name>scanlines</spirit:name>
        <spirit:wire>
          <spirit:direction>in</spirit:direction>
          <spirit:vector>
            <spirit:left spirit:format="long">1</spirit:left>
            <spirit:right spirit:format="long">0</spirit:right>
          </spirit:vector>
          <spirit:wireTypeDefs>
            <spirit:wireTypeDef>
              <spirit:typeName>wire</spirit:typeName>
              <spirit:viewNameRef>xilinx_anylanguagesynthesis</spirit:viewNameRef>
              <spirit:viewNameRef>xilinx_anylanguagebehavioralsimulation</spirit:viewNameRef>
            </spirit:wireTypeDef>
          </spirit:wireTypeDefs>
          <spirit:driver>
            <spirit:defaultValue spirit:format="long">0</spirit:defaultValue>
          </spirit:driver>
        </spirit:wire>
      </spirit:port>
      <spirit:port>
        <spirit:name>vs</spirit:name>
        <spirit:wire>
          <spirit:direction>out</spirit:direction>
          <spirit:wireTypeDefs>
            <spirit:wireTypeDef>
              <spirit:typeName>wire</spirit:typeName>
              <spirit:viewNameRef>xilinx_anylanguagesynthesis</spirit:viewNameRef>
              <spirit:viewNameRef>xilinx_anylanguagebehavioralsimulation</spirit:viewNameRef>
            </spirit:wireTypeDef>
          </spirit:wireTypeDefs>
        </spirit:wire>
      </spirit:port>
      <spirit:port>
        <spirit:name>vsync_n</spirit:name>
        <spirit:wire>
          <spirit:direction>in</spirit:direction>
          <spirit:wireTypeDefs>
            <spirit:wireTypeDef>
              <spirit:typeName>wire</spirit:typeName>
              <spirit:viewNameRef>xilinx_anylanguagesynthesis</spirit:viewNameRef>
              <spirit:viewNameRef>xilinx_anylanguagebehavioralsimulation</spirit:viewNameRef>
            </spirit:wireTypeDef>
          </spirit:wireTypeDefs>
          <spirit:driver>
            <spirit:defaultValue spirit:format="long">1</spirit:defaultValue>
          </spirit:driver>
        </spirit:wire>
      </spirit:port>
    </spirit:ports>
  </spirit:model>
  <spirit:fileSets>
    <spirit:fileSet>
      <spirit:name>xilinx_anylanguagesynthesis_view_fileset</spirit:name>
      <spirit:file>
        <spirit:name>../../ipshared/eb9b/zxvideo.gen/sources_1/bd/zxvideo/ip/zxvideo_front_porch_0_0/synth/zxvideo_front_porch_0_0.v</spirit:name>
        <spirit:fileType>verilogSource</spirit:fileType>
      </spirit:file>
      <spirit:file>
        <spirit:name>../../ipshared/eb9b/zxvideo.gen/sources_1/bd/zxvideo/ip/zxvideo_scan_convert_0_0/synth/zxvideo_scan_convert_0_0.v</spirit:name>
        <spirit:fileType>verilogSource</spirit:fileType>
      </spirit:file>
      <spirit:file>
        <spirit:name>../../ipshared/eb9b/zxvideo.gen/sources_1/bd/zxvideo/ip/zxvideo_scandoubler_0_0/synth/zxvideo_scandoubler_0_0.v</spirit:name>
        <spirit:fileType>verilogSource</spirit:fileType>
      </spirit:file>
      <spirit:file>
        <spirit:name>../../ipshared/eb9b/zxvideo.gen/sources_1/bd/zxvideo/ip/zxvideo_s_fix_0_0/synth/zxvideo_s_fix_0_0.v</spirit:name>
        <spirit:fileType>verilogSource</spirit:fileType>
      </spirit:file>
      <spirit:file>
        <spirit:name>../../ipshared/eb9b/zxvideo.gen/sources_1/bd/zxvideo/ip/zxvideo_s_fix_1_0/synth/zxvideo_s_fix_1_0.v</spirit:name>
        <spirit:fileType>verilogSource</spirit:fileType>
      </spirit:file>
      <spirit:file>
        <spirit:name>../../ipshared/eb9b/zxvideo.srcs/sources_1/new/front_porch.v</spirit:name>
        <spirit:fileType>verilogSource</spirit:fileType>
      </spirit:file>
      <spirit:file>
        <spirit:name>../../ipshared/eb9b/zxvideo.srcs/sources_1/imports/ZXNext/ram/dpram2.vhd</spirit:name>
        <spirit:fileType>vhdlSource</spirit:fileType>
      </spirit:file>
      <spirit:file>
        <spirit:name>../../ipshared/eb9b/zxvideo.srcs/sources_1/imports/ZXNext/vga/scan_convert.vhd</spirit:name>
        <spirit:fileType>vhdlSource</spirit:fileType>
      </spirit:file>
      <spirit:file>
        <spirit:name>../../ipshared/eb9b/zxvideo.srcs/sources_1/new/scandoubler.v</spirit:name>
        <spirit:fileType>verilogSource</spirit:fileType>
      </spirit:file>
      <spirit:file>
        <spirit:name>../../ipshared/eb9b/zxvideo.srcs/sources_1/imports/MISTer/video_cleaner.v</spirit:name>
        <spirit:fileType>verilogSource</spirit:fileType>
      </spirit:file>
      <spirit:file>
        <spirit:name>../../ipshared/eb9b/zxvideo.gen/sources_1/bd/zxvideo/synth/zxvideo.v</spirit:name>
        <spirit:fileType>verilogSource</spirit:fileType>
      </spirit:file>
      <spirit:file>
        <spirit:name>zxvideo.gen/sources_1/bd/zxvideo/zxvideo_ooc.xdc</spirit:name>
        <spirit:userFileType>xdc</spirit:userFileType>
        <spirit:userFileType>SCOPED_TO_REF_zxvideo</spirit:userFileType>
        <spirit:userFileType>USED_IN_out_of_context</spirit:userFileType>
      </spirit:file>
      <spirit:file>
        <spirit:name>../../ipshared/eb9b/zxvideo.gen/sources_1/bd/zxvideo/hdl/zxvideo_wrapper.v</spirit:name>
        <spirit:fileType>verilogSource</spirit:fileType>
      </spirit:file>
    </spirit:fileSet>
    <spirit:fileSet>
      <spirit:name>xilinx_verilogsynthesiswrapper_view_fileset</spirit:name>
      <spirit:file>
        <spirit:name>synth/zxnexys_zxvideo_0_0.v</spirit:name>
        <spirit:fileType>verilogSource</spirit:fileType>
        <spirit:logicalName>xil_defaultlib</spirit:logicalName>
      </spirit:file>
    </spirit:fileSet>
    <spirit:fileSet>
      <spirit:name>xilinx_anylanguagebehavioralsimulation_view_fileset</spirit:name>
      <spirit:file>
        <spirit:name>../../ipshared/eb9b/zxvideo.gen/sources_1/bd/zxvideo/ip/zxvideo_front_porch_0_0/sim/zxvideo_front_porch_0_0.v</spirit:name>
        <spirit:fileType>verilogSource</spirit:fileType>
      </spirit:file>
      <spirit:file>
        <spirit:name>../../ipshared/eb9b/zxvideo.gen/sources_1/bd/zxvideo/ip/zxvideo_scan_convert_0_0/sim/zxvideo_scan_convert_0_0.v</spirit:name>
        <spirit:fileType>verilogSource</spirit:fileType>
      </spirit:file>
      <spirit:file>
        <spirit:name>../../ipshared/eb9b/zxvideo.gen/sources_1/bd/zxvideo/ip/zxvideo_scandoubler_0_0/sim/zxvideo_scandoubler_0_0.v</spirit:name>
        <spirit:fileType>verilogSource</spirit:fileType>
      </spirit:file>
      <spirit:file>
        <spirit:name>../../ipshared/eb9b/zxvideo.gen/sources_1/bd/zxvideo/ip/zxvideo_s_fix_0_0/sim/zxvideo_s_fix_0_0.v</spirit:name>
        <spirit:fileType>verilogSource</spirit:fileType>
      </spirit:file>
      <spirit:file>
        <spirit:name>../../ipshared/eb9b/zxvideo.gen/sources_1/bd/zxvideo/ip/zxvideo_s_fix_1_0/sim/zxvideo_s_fix_1_0.v</spirit:name>
        <spirit:fileType>verilogSource</spirit:fileType>
      </spirit:file>
      <spirit:file>
        <spirit:name>../../ipshared/eb9b/zxvideo.srcs/sources_1/new/front_porch.v</spirit:name>
        <spirit:fileType>verilogSource</spirit:fileType>
      </spirit:file>
      <spirit:file>
        <spirit:name>../../ipshared/eb9b/zxvideo.srcs/sources_1/imports/ZXNext/ram/dpram2.vhd</spirit:name>
        <spirit:fileType>vhdlSource</spirit:fileType>
      </spirit:file>
      <spirit:file>
        <spirit:name>../../ipshared/eb9b/zxvideo.srcs/sources_1/imports/ZXNext/vga/scan_convert.vhd</spirit:name>
        <spirit:fileType>vhdlSource</spirit:fileType>
      </spirit:file>
      <spirit:file>
        <spirit:name>../../ipshared/eb9b/zxvideo.srcs/sources_1/new/scandoubler.v</spirit:name>
        <spirit:fileType>verilogSource</spirit:fileType>
      </spirit:file>
      <spirit:file>
        <spirit:name>../../ipshared/eb9b/zxvideo.srcs/sources_1/imports/MISTer/video_cleaner.v</spirit:name>
        <spirit:fileType>verilogSource</spirit:fileType>
      </spirit:file>
      <spirit:file>
        <spirit:name>../../ipshared/eb9b/zxvideo.gen/sources_1/bd/zxvideo/sim/zxvideo.v</spirit:name>
        <spirit:fileType>verilogSource</spirit:fileType>
      </spirit:file>
      <spirit:file>
        <spirit:name>../../ipshared/eb9b/zxvideo.gen/sources_1/bd/zxvideo/hdl/zxvideo_wrapper.v</spirit:name>
        <spirit:fileType>verilogSource</spirit:fileType>
      </spirit:file>
    </spirit:fileSet>
    <spirit:fileSet>
      <spirit:name>xilinx_verilogsimulationwrapper_view_fileset</spirit:name>
      <spirit:file>
        <spirit:name>sim/zxnexys_zxvideo_0_0.v</spirit:name>
        <spirit:fileType>verilogSource</spirit:fileType>
        <spirit:logicalName>xil_defaultlib</spirit:logicalName>
      </spirit:file>
    </spirit:fileSet>
    <spirit:fileSet>
      <spirit:name>xilinx_externalfiles_view_fileset</spirit:name>
      <spirit:file>
        <spirit:name>zxnexys_zxvideo_0_0.dcp</spirit:name>
        <spirit:userFileType>dcp</spirit:userFileType>
        <spirit:userFileType>USED_IN_implementation</spirit:userFileType>
        <spirit:userFileType>USED_IN_synthesis</spirit:userFileType>
        <spirit:logicalName>xil_defaultlib</spirit:logicalName>
      </spirit:file>
      <spirit:file>
        <spirit:name>zxnexys_zxvideo_0_0_sim_netlist.v</spirit:name>
        <spirit:fileType>verilogSource</spirit:fileType>
        <spirit:userFileType>USED_IN_simulation</spirit:userFileType>
        <spirit:userFileType>USED_IN_single_language</spirit:userFileType>
        <spirit:logicalName>xil_defaultlib</spirit:logicalName>
      </spirit:file>
      <spirit:file>
        <spirit:name>zxnexys_zxvideo_0_0_sim_netlist.vhdl</spirit:name>
        <spirit:fileType>vhdlSource</spirit:fileType>
        <spirit:userFileType>USED_IN_simulation</spirit:userFileType>
        <spirit:userFileType>USED_IN_single_language</spirit:userFileType>
        <spirit:logicalName>xil_defaultlib</spirit:logicalName>
      </spirit:file>
      <spirit:file>
        <spirit:name>zxnexys_zxvideo_0_0_stub.v</spirit:name>
        <spirit:fileType>verilogSource</spirit:fileType>
        <spirit:userFileType>USED_IN_synth_blackbox_stub</spirit:userFileType>
        <spirit:logicalName>xil_defaultlib</spirit:logicalName>
      </spirit:file>
      <spirit:file>
        <spirit:name>zxnexys_zxvideo_0_0_stub.vhdl</spirit:name>
        <spirit:fileType>vhdlSource</spirit:fileType>
        <spirit:userFileType>USED_IN_synth_blackbox_stub</spirit:userFileType>
        <spirit:logicalName>xil_defaultlib</spirit:logicalName>
      </spirit:file>
    </spirit:fileSet>
  </spirit:fileSets>
  <spirit:description>zxvideo_v1_1</spirit:description>
  <spirit:parameters>
    <spirit:parameter>
      <spirit:name>Component_Name</spirit:name>
      <spirit:value spirit:resolve="user" spirit:id="PARAM_VALUE.Component_Name" spirit:order="1">zxnexys_zxvideo_0_0</spirit:value>
    </spirit:parameter>
  </spirit:parameters>
  <spirit:vendorExtensions>
    <xilinx:coreExtensions>
      <xilinx:displayName>zxvideo_v1_1</xilinx:displayName>
      <xilinx:definitionSource>package_project</xilinx:definitionSource>
      <xilinx:coreRevision>7</xilinx:coreRevision>
      <xilinx:tags>
        <xilinx:tag xilinx:name="ui.data.coregen.df@375ef053_ARCHIVE_LOCATION">v:/zxnext/zxvideo</xilinx:tag>
        <xilinx:tag xilinx:name="ui.data.coregen.df@4bcf7865_ARCHIVE_LOCATION">v:/zxnext/zxvideo</xilinx:tag>
        <xilinx:tag xilinx:name="ui.data.coregen.df@61138d19_ARCHIVE_LOCATION">v:/zxnext/zxvideo</xilinx:tag>
        <xilinx:tag xilinx:name="ui.data.coregen.df@7cc1d0cf_ARCHIVE_LOCATION">v:/zxnext/zxvideo</xilinx:tag>
        <xilinx:tag xilinx:name="ui.data.coregen.df@49226f17_ARCHIVE_LOCATION">v:/zxnext/zxvideo</xilinx:tag>
        <xilinx:tag xilinx:name="ui.data.coregen.df@4d395f67_ARCHIVE_LOCATION">v:/zxnext/zxvideo</xilinx:tag>
        <xilinx:tag xilinx:name="ui.data.coregen.df@1cd64421_ARCHIVE_LOCATION">v:/zxnext/zxvideo</xilinx:tag>
        <xilinx:tag xilinx:name="ui.data.coregen.df@682b3208_ARCHIVE_LOCATION">v:/zxnext/zxvideo</xilinx:tag>
        <xilinx:tag xilinx:name="ui.data.coregen.df@40b01e8e_ARCHIVE_LOCATION">v:/zxnext/zxvideo</xilinx:tag>
        <xilinx:tag xilinx:name="ui.data.coregen.df@2956b2d6_ARCHIVE_LOCATION">v:/zxnext/zxvideo</xilinx:tag>
        <xilinx:tag xilinx:name="ui.data.coregen.df@383fc68c_ARCHIVE_LOCATION">v:/zxnext/zxvideo</xilinx:tag>
        <xilinx:tag xilinx:name="ui.data.coregen.df@34853d2e_ARCHIVE_LOCATION">v:/zxnext/zxvideo</xilinx:tag>
        <xilinx:tag xilinx:name="ui.data.coregen.df@31e5e489_ARCHIVE_LOCATION">v:/zxnext/zxvideo</xilinx:tag>
        <xilinx:tag xilinx:name="ui.data.coregen.df@5bfe87dd_ARCHIVE_LOCATION">v:/zxnext/zxvideo</xilinx:tag>
        <xilinx:tag xilinx:name="ui.data.coregen.df@6120c77e_ARCHIVE_LOCATION">v:/zxnext/zxvideo</xilinx:tag>
        <xilinx:tag xilinx:name="ui.data.coregen.df@3be22610_ARCHIVE_LOCATION">v:/zxnext/zxvideo</xilinx:tag>
        <xilinx:tag xilinx:name="ui.data.coregen.df@5d4d4653_ARCHIVE_LOCATION">v:/zxnext/zxvideo</xilinx:tag>
        <xilinx:tag xilinx:name="ui.data.coregen.df@8ab42df_ARCHIVE_LOCATION">v:/zxnext/zxvideo</xilinx:tag>
        <xilinx:tag xilinx:name="ui.data.coregen.df@7e076f43_ARCHIVE_LOCATION">v:/zxnext/zxvideo</xilinx:tag>
        <xilinx:tag xilinx:name="ui.data.coregen.df@3016259_ARCHIVE_LOCATION">v:/zxnext/zxvideo</xilinx:tag>
        <xilinx:tag xilinx:name="ui.data.coregen.df@57ee13d6_ARCHIVE_LOCATION">v:/zxnext/zxvideo</xilinx:tag>
        <xilinx:tag xilinx:name="ui.data.coregen.df@27a42b7c_ARCHIVE_LOCATION">v:/zxnext/zxvideo</xilinx:tag>
        <xilinx:tag xilinx:name="ui.data.coregen.df@c0b0a3_ARCHIVE_LOCATION">v:/zxnext/zxvideo</xilinx:tag>
        <xilinx:tag xilinx:name="ui.data.coregen.df@36a556ec_ARCHIVE_LOCATION">v:/zxnext/zxvideo</xilinx:tag>
        <xilinx:tag xilinx:name="ui.data.coregen.df@a4de90_ARCHIVE_LOCATION">v:/zxnext/zxvideo</xilinx:tag>
        <xilinx:tag xilinx:name="ui.data.coregen.df@530e78c6_ARCHIVE_LOCATION">v:/zxnext/zxvideo</xilinx:tag>
        <xilinx:tag xilinx:name="ui.data.coregen.df@4044c66a_ARCHIVE_LOCATION">v:/zxnext/zxvideo</xilinx:tag>
        <xilinx:tag xilinx:name="ui.data.coregen.df@4e2fe9a3_ARCHIVE_LOCATION">v:/zxnext/zxvideo</xilinx:tag>
        <xilinx:tag xilinx:name="ui.data.coregen.df@60f9e2c1_ARCHIVE_LOCATION">v:/zxnext/zxvideo</xilinx:tag>
        <xilinx:tag xilinx:name="ui.data.coregen.df@6dbec7e8_ARCHIVE_LOCATION">v:/zxnext/zxvideo</xilinx:tag>
        <xilinx:tag xilinx:name="ui.data.coregen.df@ff1a53d_ARCHIVE_LOCATION">v:/zxnext/zxvideo</xilinx:tag>
        <xilinx:tag xilinx:name="ui.data.coregen.df@118db36_ARCHIVE_LOCATION">v:/zxnext/zxvideo</xilinx:tag>
        <xilinx:tag xilinx:name="ui.data.coregen.df@8d3a6bd_ARCHIVE_LOCATION">v:/zxnext/zxvideo</xilinx:tag>
        <xilinx:tag xilinx:name="ui.data.coregen.df@784ad302_ARCHIVE_LOCATION">v:/zxnext/zxvideo</xilinx:tag>
        <xilinx:tag xilinx:name="ui.data.coregen.df@6de63d8_ARCHIVE_LOCATION">v:/zxnext/zxvideo</xilinx:tag>
        <xilinx:tag xilinx:name="ui.data.coregen.df@75d4a1f0_ARCHIVE_LOCATION">v:/zxnext/zxvideo</xilinx:tag>
        <xilinx:tag xilinx:name="ui.data.coregen.df@1543b5b1_ARCHIVE_LOCATION">v:/zxnext/zxvideo</xilinx:tag>
        <xilinx:tag xilinx:name="ui.data.coregen.df@59b8083d_ARCHIVE_LOCATION">v:/zxnext/zxvideo</xilinx:tag>
        <xilinx:tag xilinx:name="ui.data.coregen.df@46dce48b_ARCHIVE_LOCATION">v:/zxnext/zxvideo</xilinx:tag>
        <xilinx:tag xilinx:name="ui.data.coregen.df@53f4482e_ARCHIVE_LOCATION">v:/zxnext/zxvideo</xilinx:tag>
        <xilinx:tag xilinx:name="ui.data.coregen.df@4076fc63_ARCHIVE_LOCATION">v:/zxnext/zxvideo</xilinx:tag>
        <xilinx:tag xilinx:name="ui.data.coregen.df@6f2c81fd_ARCHIVE_LOCATION">v:/zxnext/zxvideo</xilinx:tag>
        <xilinx:tag xilinx:name="ui.data.coregen.df@2c7a4811_ARCHIVE_LOCATION">v:/zxnext/zxvideo</xilinx:tag>
        <xilinx:tag xilinx:name="ui.data.coregen.df@cc880ea_ARCHIVE_LOCATION">v:/zxnext/zxvideo</xilinx:tag>
        <xilinx:tag xilinx:name="ui.data.coregen.df@71a2c8c2_ARCHIVE_LOCATION">v:/zxnext/zxvideo</xilinx:tag>
        <xilinx:tag xilinx:name="ui.data.coregen.df@1c8b450_ARCHIVE_LOCATION">v:/zxnext/zxvideo</xilinx:tag>
        <xilinx:tag xilinx:name="ui.data.coregen.df@72291207_ARCHIVE_LOCATION">v:/zxnext/zxvideo</xilinx:tag>
        <xilinx:tag xilinx:name="ui.data.coregen.df@34aa8a3a_ARCHIVE_LOCATION">v:/zxnext/zxvideo</xilinx:tag>
        <xilinx:tag xilinx:name="ui.data.coregen.df@33a1edf3_ARCHIVE_LOCATION">v:/zxnext/zxvideo</xilinx:tag>
        <xilinx:tag xilinx:name="ui.data.coregen.df@7fb2efd4_ARCHIVE_LOCATION">v:/zxnext/zxvideo</xilinx:tag>
        <xilinx:tag xilinx:name="ui.data.coregen.df@78ab2fd1_ARCHIVE_LOCATION">v:/zxnext/zxvideo</xilinx:tag>
        <xilinx:tag xilinx:name="ui.data.coregen.df@600bc223_ARCHIVE_LOCATION">v:/zxnext/zxvideo</xilinx:tag>
        <xilinx:tag xilinx:name="ui.data.coregen.df@1be252dd_ARCHIVE_LOCATION">v:/zxnext/zxvideo</xilinx:tag>
        <xilinx:tag xilinx:name="ui.data.coregen.df@22220b04_ARCHIVE_LOCATION">v:/zxnext/zxvideo</xilinx:tag>
        <xilinx:tag xilinx:name="ui.data.coregen.df@3f5beb78_ARCHIVE_LOCATION">v:/zxnext/zxvideo</xilinx:tag>
        <xilinx:tag xilinx:name="ui.data.coregen.df@64658146_ARCHIVE_LOCATION">v:/zxnext/zxvideo</xilinx:tag>
        <xilinx:tag xilinx:name="ui.data.coregen.df@1277fe81_ARCHIVE_LOCATION">v:/zxnext/zxvideo</xilinx:tag>
        <xilinx:tag xilinx:name="ui.data.coregen.df@7fe82e6_ARCHIVE_LOCATION">v:/zxnext/zxvideo</xilinx:tag>
        <xilinx:tag xilinx:name="ui.data.coregen.df@7505fbab_ARCHIVE_LOCATION">v:/zxnext/zxvideo</xilinx:tag>
        <xilinx:tag xilinx:name="ui.data.coregen.df@2e63a1ff_ARCHIVE_LOCATION">v:/zxnext/zxvideo</xilinx:tag>
        <xilinx:tag xilinx:name="ui.data.coregen.df@1742b64c_ARCHIVE_LOCATION">v:/zxnext/zxvideo</xilinx:tag>
        <xilinx:tag xilinx:name="ui.data.coregen.df@692ca524_ARCHIVE_LOCATION">v:/zxnext/zxvideo</xilinx:tag>
        <xilinx:tag xilinx:name="ui.data.coregen.df@7ffbb104_ARCHIVE_LOCATION">v:/zxnext/zxvideo</xilinx:tag>
        <xilinx:tag xilinx:name="ui.data.coregen.df@7558cc55_ARCHIVE_LOCATION">v:/zxnext/zxvideo</xilinx:tag>
        <xilinx:tag xilinx:name="ui.data.coregen.df@737021d1_ARCHIVE_LOCATION">v:/zxnext/zxvideo</xilinx:tag>
        <xilinx:tag xilinx:name="ui.data.coregen.df@32a1e4ad_ARCHIVE_LOCATION">v:/zxnext/zxvideo</xilinx:tag>
        <xilinx:tag xilinx:name="ui.data.coregen.df@f4d85e9_ARCHIVE_LOCATION">v:/zxnext/zxvideo</xilinx:tag>
        <xilinx:tag xilinx:name="ui.data.coregen.df@35bd23ac_ARCHIVE_LOCATION">v:/zxnext/zxvideo</xilinx:tag>
        <xilinx:tag xilinx:name="ui.data.coregen.df@8193cf3_ARCHIVE_LOCATION">v:/zxnext/zxvideo</xilinx:tag>
        <xilinx:tag xilinx:name="ui.data.coregen.df@2eea36dc_ARCHIVE_LOCATION">v:/zxnext/zxvideo</xilinx:tag>
        <xilinx:tag xilinx:name="ui.data.coregen.df@3975ccd7_ARCHIVE_LOCATION">v:/zxnext/zxvideo</xilinx:tag>
        <xilinx:tag xilinx:name="ui.data.coregen.df@7409efc6_ARCHIVE_LOCATION">v:/zxnext/zxvideo</xilinx:tag>
        <xilinx:tag xilinx:name="ui.data.coregen.df@7b225642_ARCHIVE_LOCATION">v:/zxnext/zxvideo</xilinx:tag>
        <xilinx:tag xilinx:name="ui.data.coregen.df@17c7f0ed_ARCHIVE_LOCATION">v:/zxnext/zxvideo</xilinx:tag>
        <xilinx:tag xilinx:name="ui.data.coregen.df@79f2f6cb_ARCHIVE_LOCATION">v:/zxnext/zxvideo</xilinx:tag>
        <xilinx:tag xilinx:name="ui.data.coregen.df@ce13c27_ARCHIVE_LOCATION">v:/zxnext/zxvideo</xilinx:tag>
        <xilinx:tag xilinx:name="ui.data.coregen.df@3cbaa653_ARCHIVE_LOCATION">v:/zxnext/zxvideo</xilinx:tag>
        <xilinx:tag xilinx:name="ui.data.coregen.df@457eeac_ARCHIVE_LOCATION">v:/zxnext/zxvideo</xilinx:tag>
        <xilinx:tag xilinx:name="ui.data.coregen.df@50f4d4ae_ARCHIVE_LOCATION">v:/zxnext/zxvideo</xilinx:tag>
        <xilinx:tag xilinx:name="ui.data.coregen.df@40e075f_ARCHIVE_LOCATION">v:/zxnext/zxvideo</xilinx:tag>
        <xilinx:tag xilinx:name="ui.data.coregen.df@778a1d4a_ARCHIVE_LOCATION">v:/zxnext/zxvideo</xilinx:tag>
        <xilinx:tag xilinx:name="ui.data.coregen.df@67c409c7_ARCHIVE_LOCATION">v:/zxnext/zxvideo</xilinx:tag>
        <xilinx:tag xilinx:name="ui.data.coregen.df@3cdc74ee_ARCHIVE_LOCATION">v:/zxnext/zxvideo</xilinx:tag>
        <xilinx:tag xilinx:name="ui.data.coregen.df@6bf3985b_ARCHIVE_LOCATION">v:/zxnext/zxvideo</xilinx:tag>
        <xilinx:tag xilinx:name="ui.data.coregen.df@35b42534_ARCHIVE_LOCATION">v:/zxnext/zxvideo</xilinx:tag>
        <xilinx:tag xilinx:name="ui.data.coregen.df@31bc638_ARCHIVE_LOCATION">v:/zxnext/zxvideo</xilinx:tag>
        <xilinx:tag xilinx:name="ui.data.coregen.df@21db3ab9_ARCHIVE_LOCATION">v:/zxnext/zxvideo</xilinx:tag>
        <xilinx:tag xilinx:name="ui.data.coregen.df@195865cc_ARCHIVE_LOCATION">v:/zxnext/zxvideo</xilinx:tag>
        <xilinx:tag xilinx:name="ui.data.coregen.df@2055587f_ARCHIVE_LOCATION">v:/zxnext/zxvideo</xilinx:tag>
        <xilinx:tag xilinx:name="ui.data.coregen.df@6f635aa3_ARCHIVE_LOCATION">v:/zxnext/zxvideo</xilinx:tag>
        <xilinx:tag xilinx:name="ui.data.coregen.df@26c932e9_ARCHIVE_LOCATION">v:/zxnext/zxvideo</xilinx:tag>
        <xilinx:tag xilinx:name="ui.data.coregen.df@27b8e32d_ARCHIVE_LOCATION">v:/zxnext/zxvideo</xilinx:tag>
        <xilinx:tag xilinx:name="ui.data.coregen.df@4e48a462_ARCHIVE_LOCATION">v:/zxnext/zxvideo</xilinx:tag>
        <xilinx:tag xilinx:name="ui.data.coregen.df@9ba4cc5_ARCHIVE_LOCATION">v:/zxnext/zxvideo</xilinx:tag>
        <xilinx:tag xilinx:name="ui.data.coregen.df@4d94ee75_ARCHIVE_LOCATION">v:/zxnext/zxvideo</xilinx:tag>
        <xilinx:tag xilinx:name="ui.data.coregen.df@7ace28ab_ARCHIVE_LOCATION">v:/zxnext/zxvideo</xilinx:tag>
        <xilinx:tag xilinx:name="ui.data.coregen.df@29332f63_ARCHIVE_LOCATION">v:/zxnext/zxvideo</xilinx:tag>
        <xilinx:tag xilinx:name="ui.data.coregen.df@2261b484_ARCHIVE_LOCATION">v:/zxnext/zxvideo</xilinx:tag>
        <xilinx:tag xilinx:name="ui.data.coregen.df@67de2661_ARCHIVE_LOCATION">v:/zxnext/zxvideo</xilinx:tag>
        <xilinx:tag xilinx:name="ui.data.coregen.df@9e81b21_ARCHIVE_LOCATION">v:/zxnext/zxvideo</xilinx:tag>
        <xilinx:tag xilinx:name="ui.data.coregen.df@e7bea48_ARCHIVE_LOCATION">v:/zxnext/zxvideo</xilinx:tag>
        <xilinx:tag xilinx:name="ui.data.coregen.df@4ff75b27_ARCHIVE_LOCATION">v:/zxnext/zxvideo</xilinx:tag>
        <xilinx:tag xilinx:name="ui.data.coregen.df@53aff7b1_ARCHIVE_LOCATION">v:/zxnext/zxvideo</xilinx:tag>
        <xilinx:tag xilinx:name="ui.data.coregen.df@54a8954_ARCHIVE_LOCATION">v:/zxnext/zxvideo</xilinx:tag>
        <xilinx:tag xilinx:name="ui.data.coregen.df@5bae785e_ARCHIVE_LOCATION">v:/zxnext/zxvideo</xilinx:tag>
        <xilinx:tag xilinx:name="ui.data.coregen.df@7a6e2e9c_ARCHIVE_LOCATION">v:/zxnext/zxvideo</xilinx:tag>
        <xilinx:tag xilinx:name="ui.data.coregen.df@3468f895_ARCHIVE_LOCATION">v:/zxnext/zxvideo</xilinx:tag>
        <xilinx:tag xilinx:name="ui.data.coregen.df@46699199_ARCHIVE_LOCATION">v:/zxnext/zxvideo</xilinx:tag>
        <xilinx:tag xilinx:name="ui.data.coregen.df@4bce758c_ARCHIVE_LOCATION">v:/zxnext/zxvideo</xilinx:tag>
        <xilinx:tag xilinx:name="ui.data.coregen.df@54f251ba_ARCHIVE_LOCATION">v:/zxnext/zxvideo</xilinx:tag>
        <xilinx:tag xilinx:name="ui.data.coregen.df@9129c6b_ARCHIVE_LOCATION">v:/zxnext/zxvideo</xilinx:tag>
        <xilinx:tag xilinx:name="ui.data.coregen.df@62cded28_ARCHIVE_LOCATION">v:/zxnext/zxvideo</xilinx:tag>
        <xilinx:tag xilinx:name="ui.data.coregen.df@5c9db92d_ARCHIVE_LOCATION">v:/zxnext/zxvideo</xilinx:tag>
        <xilinx:tag xilinx:name="ui.data.coregen.df@51373d65_ARCHIVE_LOCATION">v:/zxnext/zxvideo</xilinx:tag>
        <xilinx:tag xilinx:name="ui.data.coregen.df@4b6fdd11_ARCHIVE_LOCATION">v:/zxnext/zxvideo</xilinx:tag>
        <xilinx:tag xilinx:name="ui.data.coregen.df@2e472663_ARCHIVE_LOCATION">v:/zxnext/zxvideo</xilinx:tag>
      </xilinx:tags>
      <xilinx:configElementInfos>
        <xilinx:configElementInfo xilinx:referenceId="BUSIFPARAM_VALUE.CLK_PERIPHERAL.ASSOCIATED_BUSIF" xilinx:valuePermission="bd_and_user"/>
        <xilinx:configElementInfo xilinx:referenceId="BUSIFPARAM_VALUE.CLK_PERIPHERAL.ASSOCIATED_PORT" xilinx:valuePermission="bd_and_user"/>
        <xilinx:configElementInfo xilinx:referenceId="BUSIFPARAM_VALUE.CLK_PERIPHERAL.ASSOCIATED_RESET" xilinx:valuePermission="bd_and_user"/>
        <xilinx:configElementInfo xilinx:referenceId="BUSIFPARAM_VALUE.CLK_PERIPHERAL.CLK_DOMAIN" xilinx:valueSource="default_prop" xilinx:valuePermission="bd_and_user"/>
        <xilinx:configElementInfo xilinx:referenceId="BUSIFPARAM_VALUE.CLK_PERIPHERAL.FREQ_HZ" xilinx:valuePermission="bd_and_user"/>
        <xilinx:configElementInfo xilinx:referenceId="BUSIFPARAM_VALUE.CLK_PERIPHERAL.FREQ_TOLERANCE_HZ" xilinx:valuePermission="bd_and_user"/>
        <xilinx:configElementInfo xilinx:referenceId="BUSIFPARAM_VALUE.CLK_PERIPHERAL.PHASE" xilinx:valuePermission="bd_and_user"/>
        <xilinx:configElementInfo xilinx:referenceId="BUSIFPARAM_VALUE.CLK_PERIPHERAL_N.ASSOCIATED_BUSIF" xilinx:valuePermission="bd_and_user"/>
        <xilinx:configElementInfo xilinx:referenceId="BUSIFPARAM_VALUE.CLK_PERIPHERAL_N.ASSOCIATED_PORT" xilinx:valuePermission="bd_and_user"/>
        <xilinx:configElementInfo xilinx:referenceId="BUSIFPARAM_VALUE.CLK_PERIPHERAL_N.ASSOCIATED_RESET" xilinx:valuePermission="bd_and_user"/>
        <xilinx:configElementInfo xilinx:referenceId="BUSIFPARAM_VALUE.CLK_PERIPHERAL_N.CLK_DOMAIN" xilinx:valueSource="default_prop" xilinx:valuePermission="bd_and_user"/>
        <xilinx:configElementInfo xilinx:referenceId="BUSIFPARAM_VALUE.CLK_PERIPHERAL_N.FREQ_HZ" xilinx:valuePermission="bd_and_user"/>
        <xilinx:configElementInfo xilinx:referenceId="BUSIFPARAM_VALUE.CLK_PERIPHERAL_N.FREQ_TOLERANCE_HZ" xilinx:valuePermission="bd_and_user"/>
        <xilinx:configElementInfo xilinx:referenceId="BUSIFPARAM_VALUE.CLK_PERIPHERAL_N.PHASE" xilinx:valuePermission="bd_and_user"/>
        <xilinx:configElementInfo xilinx:referenceId="BUSIFPARAM_VALUE.CLK_VIDEO.ASSOCIATED_BUSIF" xilinx:valuePermission="bd_and_user"/>
        <xilinx:configElementInfo xilinx:referenceId="BUSIFPARAM_VALUE.CLK_VIDEO.ASSOCIATED_PORT" xilinx:valuePermission="bd_and_user"/>
        <xilinx:configElementInfo xilinx:referenceId="BUSIFPARAM_VALUE.CLK_VIDEO.ASSOCIATED_RESET" xilinx:valuePermission="bd_and_user"/>
        <xilinx:configElementInfo xilinx:referenceId="BUSIFPARAM_VALUE.CLK_VIDEO.CLK_DOMAIN" xilinx:valueSource="default_prop" xilinx:valuePermission="bd_and_user"/>
        <xilinx:configElementInfo xilinx:referenceId="BUSIFPARAM_VALUE.CLK_VIDEO.FREQ_HZ" xilinx:valuePermission="bd_and_user"/>
        <xilinx:configElementInfo xilinx:referenceId="BUSIFPARAM_VALUE.CLK_VIDEO.FREQ_TOLERANCE_HZ" xilinx:valuePermission="bd_and_user"/>
        <xilinx:configElementInfo xilinx:referenceId="BUSIFPARAM_VALUE.CLK_VIDEO.PHASE" xilinx:valuePermission="bd_and_user"/>
      </xilinx:configElementInfos>
    </xilinx:coreExtensions>
    <xilinx:packagingInfo>
      <xilinx:xilinxVersion>2021.2</xilinx:xilinxVersion>
      <xilinx:checksum xilinx:scope="busInterfaces" xilinx:value="a45ab934"/>
      <xilinx:checksum xilinx:scope="fileGroups" xilinx:value="378a2885"/>
      <xilinx:checksum xilinx:scope="ports" xilinx:value="0fbd3c1c"/>
      <xilinx:checksum xilinx:scope="parameters" xilinx:value="e63f4202"/>
    </xilinx:packagingInfo>
  </spirit:vendorExtensions>
</spirit:component>
