<?xml version="1.0" encoding="UTF-8"?>
<spirit:component xmlns:xilinx="http://www.xilinx.com" xmlns:spirit="http://www.spiritconsortium.org/XMLSchema/SPIRIT/1685-2009" xmlns:xsi="http://www.w3.org/2001/XMLSchema-instance">
  <spirit:vendor>specnext.com</spirit:vendor>
  <spirit:library>customized_ip</spirit:library>
  <spirit:name>zxnexys_pmod_xsd_0_0</spirit:name>
  <spirit:version>1.0</spirit:version>
  <spirit:busInterfaces>
    <spirit:busInterface>
      <spirit:name>pmod_xsd</spirit:name>
      <spirit:busType spirit:vendor="digilentinc.com" spirit:library="interface" spirit:name="pmod" spirit:version="1.0"/>
      <spirit:abstractionType spirit:vendor="digilentinc.com" spirit:library="interface" spirit:name="pmod_rtl" spirit:version="1.0"/>
      <spirit:master/>
      <spirit:portMaps>
        <spirit:portMap>
          <spirit:logicalPort>
            <spirit:name>PIN1_I</spirit:name>
          </spirit:logicalPort>
          <spirit:physicalPort>
            <spirit:name>pin1_i</spirit:name>
          </spirit:physicalPort>
        </spirit:portMap>
        <spirit:portMap>
          <spirit:logicalPort>
            <spirit:name>PIN1_O</spirit:name>
          </spirit:logicalPort>
          <spirit:physicalPort>
            <spirit:name>pin1_o</spirit:name>
          </spirit:physicalPort>
        </spirit:portMap>
        <spirit:portMap>
          <spirit:logicalPort>
            <spirit:name>PIN1_T</spirit:name>
          </spirit:logicalPort>
          <spirit:physicalPort>
            <spirit:name>pin1_t</spirit:name>
          </spirit:physicalPort>
        </spirit:portMap>
        <spirit:portMap>
          <spirit:logicalPort>
            <spirit:name>PIN2_I</spirit:name>
          </spirit:logicalPort>
          <spirit:physicalPort>
            <spirit:name>pin2_i</spirit:name>
          </spirit:physicalPort>
        </spirit:portMap>
        <spirit:portMap>
          <spirit:logicalPort>
            <spirit:name>PIN2_O</spirit:name>
          </spirit:logicalPort>
          <spirit:physicalPort>
            <spirit:name>pin2_o</spirit:name>
          </spirit:physicalPort>
        </spirit:portMap>
        <spirit:portMap>
          <spirit:logicalPort>
            <spirit:name>PIN2_T</spirit:name>
          </spirit:logicalPort>
          <spirit:physicalPort>
            <spirit:name>pin2_t</spirit:name>
          </spirit:physicalPort>
        </spirit:portMap>
        <spirit:portMap>
          <spirit:logicalPort>
            <spirit:name>PIN3_I</spirit:name>
          </spirit:logicalPort>
          <spirit:physicalPort>
            <spirit:name>pin3_i</spirit:name>
          </spirit:physicalPort>
        </spirit:portMap>
        <spirit:portMap>
          <spirit:logicalPort>
            <spirit:name>PIN3_O</spirit:name>
          </spirit:logicalPort>
          <spirit:physicalPort>
            <spirit:name>pin3_o</spirit:name>
          </spirit:physicalPort>
        </spirit:portMap>
        <spirit:portMap>
          <spirit:logicalPort>
            <spirit:name>PIN3_T</spirit:name>
          </spirit:logicalPort>
          <spirit:physicalPort>
            <spirit:name>pin3_t</spirit:name>
          </spirit:physicalPort>
        </spirit:portMap>
        <spirit:portMap>
          <spirit:logicalPort>
            <spirit:name>PIN4_I</spirit:name>
          </spirit:logicalPort>
          <spirit:physicalPort>
            <spirit:name>pin4_i</spirit:name>
          </spirit:physicalPort>
        </spirit:portMap>
        <spirit:portMap>
          <spirit:logicalPort>
            <spirit:name>PIN4_O</spirit:name>
          </spirit:logicalPort>
          <spirit:physicalPort>
            <spirit:name>pin4_o</spirit:name>
          </spirit:physicalPort>
        </spirit:portMap>
        <spirit:portMap>
          <spirit:logicalPort>
            <spirit:name>PIN4_T</spirit:name>
          </spirit:logicalPort>
          <spirit:physicalPort>
            <spirit:name>pin4_t</spirit:name>
          </spirit:physicalPort>
        </spirit:portMap>
        <spirit:portMap>
          <spirit:logicalPort>
            <spirit:name>PIN7_I</spirit:name>
          </spirit:logicalPort>
          <spirit:physicalPort>
            <spirit:name>pin7_i</spirit:name>
          </spirit:physicalPort>
        </spirit:portMap>
        <spirit:portMap>
          <spirit:logicalPort>
            <spirit:name>PIN7_O</spirit:name>
          </spirit:logicalPort>
          <spirit:physicalPort>
            <spirit:name>pin7_o</spirit:name>
          </spirit:physicalPort>
        </spirit:portMap>
        <spirit:portMap>
          <spirit:logicalPort>
            <spirit:name>PIN7_T</spirit:name>
          </spirit:logicalPort>
          <spirit:physicalPort>
            <spirit:name>pin7_t</spirit:name>
          </spirit:physicalPort>
        </spirit:portMap>
        <spirit:portMap>
          <spirit:logicalPort>
            <spirit:name>PIN8_I</spirit:name>
          </spirit:logicalPort>
          <spirit:physicalPort>
            <spirit:name>pin8_i</spirit:name>
          </spirit:physicalPort>
        </spirit:portMap>
        <spirit:portMap>
          <spirit:logicalPort>
            <spirit:name>PIN8_O</spirit:name>
          </spirit:logicalPort>
          <spirit:physicalPort>
            <spirit:name>pin8_o</spirit:name>
          </spirit:physicalPort>
        </spirit:portMap>
        <spirit:portMap>
          <spirit:logicalPort>
            <spirit:name>PIN8_T</spirit:name>
          </spirit:logicalPort>
          <spirit:physicalPort>
            <spirit:name>pin8_t</spirit:name>
          </spirit:physicalPort>
        </spirit:portMap>
        <spirit:portMap>
          <spirit:logicalPort>
            <spirit:name>PIN9_I</spirit:name>
          </spirit:logicalPort>
          <spirit:physicalPort>
            <spirit:name>pin9_i</spirit:name>
          </spirit:physicalPort>
        </spirit:portMap>
        <spirit:portMap>
          <spirit:logicalPort>
            <spirit:name>PIN9_O</spirit:name>
          </spirit:logicalPort>
          <spirit:physicalPort>
            <spirit:name>pin9_o</spirit:name>
          </spirit:physicalPort>
        </spirit:portMap>
        <spirit:portMap>
          <spirit:logicalPort>
            <spirit:name>PIN9_T</spirit:name>
          </spirit:logicalPort>
          <spirit:physicalPort>
            <spirit:name>pin9_t</spirit:name>
          </spirit:physicalPort>
        </spirit:portMap>
        <spirit:portMap>
          <spirit:logicalPort>
            <spirit:name>PIN10_I</spirit:name>
          </spirit:logicalPort>
          <spirit:physicalPort>
            <spirit:name>pin10_i</spirit:name>
          </spirit:physicalPort>
        </spirit:portMap>
        <spirit:portMap>
          <spirit:logicalPort>
            <spirit:name>PIN10_O</spirit:name>
          </spirit:logicalPort>
          <spirit:physicalPort>
            <spirit:name>pin10_o</spirit:name>
          </spirit:physicalPort>
        </spirit:portMap>
        <spirit:portMap>
          <spirit:logicalPort>
            <spirit:name>PIN10_T</spirit:name>
          </spirit:logicalPort>
          <spirit:physicalPort>
            <spirit:name>pin10_t</spirit:name>
          </spirit:physicalPort>
        </spirit:portMap>
      </spirit:portMaps>
    </spirit:busInterface>
  </spirit:busInterfaces>
  <spirit:model>
    <spirit:views>
      <spirit:view>
        <spirit:name>xilinx_anylanguagesynthesis</spirit:name>
        <spirit:displayName>Synthesis</spirit:displayName>
        <spirit:envIdentifier>:vivado.xilinx.com:synthesis</spirit:envIdentifier>
        <spirit:modelName>pmod_xsd</spirit:modelName>
        <spirit:fileSetRef>
          <spirit:localName>xilinx_anylanguagesynthesis_view_fileset</spirit:localName>
        </spirit:fileSetRef>
        <spirit:parameters>
          <spirit:parameter>
            <spirit:name>GENtimestamp</spirit:name>
            <spirit:value>Wed Mar 16 11:10:20 UTC 2022</spirit:value>
          </spirit:parameter>
          <spirit:parameter>
            <spirit:name>outputProductCRC</spirit:name>
            <spirit:value>9:dc6d78a3</spirit:value>
          </spirit:parameter>
        </spirit:parameters>
      </spirit:view>
      <spirit:view>
        <spirit:name>xilinx_synthesisconstraints</spirit:name>
        <spirit:displayName>Synthesis Constraints</spirit:displayName>
        <spirit:envIdentifier>:vivado.xilinx.com:synthesis.constraints</spirit:envIdentifier>
        <spirit:parameters>
          <spirit:parameter>
            <spirit:name>outputProductCRC</spirit:name>
            <spirit:value>9:dc6d78a3</spirit:value>
          </spirit:parameter>
        </spirit:parameters>
      </spirit:view>
      <spirit:view>
        <spirit:name>xilinx_verilogsynthesiswrapper</spirit:name>
        <spirit:displayName>Verilog Synthesis Wrapper</spirit:displayName>
        <spirit:envIdentifier>verilogSource:vivado.xilinx.com:synthesis.wrapper</spirit:envIdentifier>
        <spirit:language>verilog</spirit:language>
        <spirit:modelName>zxnexys_pmod_xsd_0_0</spirit:modelName>
        <spirit:fileSetRef>
          <spirit:localName>xilinx_verilogsynthesiswrapper_view_fileset</spirit:localName>
        </spirit:fileSetRef>
        <spirit:parameters>
          <spirit:parameter>
            <spirit:name>GENtimestamp</spirit:name>
            <spirit:value>Wed Mar 16 11:10:20 UTC 2022</spirit:value>
          </spirit:parameter>
          <spirit:parameter>
            <spirit:name>outputProductCRC</spirit:name>
            <spirit:value>9:dc6d78a3</spirit:value>
          </spirit:parameter>
        </spirit:parameters>
      </spirit:view>
      <spirit:view>
        <spirit:name>xilinx_anylanguagebehavioralsimulation</spirit:name>
        <spirit:displayName>Simulation</spirit:displayName>
        <spirit:envIdentifier>:vivado.xilinx.com:simulation</spirit:envIdentifier>
        <spirit:modelName>pmod_xsd</spirit:modelName>
        <spirit:fileSetRef>
          <spirit:localName>xilinx_anylanguagebehavioralsimulation_view_fileset</spirit:localName>
        </spirit:fileSetRef>
        <spirit:parameters>
          <spirit:parameter>
            <spirit:name>GENtimestamp</spirit:name>
            <spirit:value>Wed Mar 16 11:10:20 UTC 2022</spirit:value>
          </spirit:parameter>
          <spirit:parameter>
            <spirit:name>outputProductCRC</spirit:name>
            <spirit:value>9:cb009e5a</spirit:value>
          </spirit:parameter>
        </spirit:parameters>
      </spirit:view>
      <spirit:view>
        <spirit:name>xilinx_verilogsimulationwrapper</spirit:name>
        <spirit:displayName>Verilog Simulation Wrapper</spirit:displayName>
        <spirit:envIdentifier>verilogSource:vivado.xilinx.com:simulation.wrapper</spirit:envIdentifier>
        <spirit:language>verilog</spirit:language>
        <spirit:modelName>zxnexys_pmod_xsd_0_0</spirit:modelName>
        <spirit:fileSetRef>
          <spirit:localName>xilinx_verilogsimulationwrapper_view_fileset</spirit:localName>
        </spirit:fileSetRef>
        <spirit:parameters>
          <spirit:parameter>
            <spirit:name>GENtimestamp</spirit:name>
            <spirit:value>Wed Mar 16 11:10:20 UTC 2022</spirit:value>
          </spirit:parameter>
          <spirit:parameter>
            <spirit:name>outputProductCRC</spirit:name>
            <spirit:value>9:cb009e5a</spirit:value>
          </spirit:parameter>
        </spirit:parameters>
      </spirit:view>
      <spirit:view>
        <spirit:name>xilinx_externalfiles</spirit:name>
        <spirit:displayName>External Files</spirit:displayName>
        <spirit:envIdentifier>:vivado.xilinx.com:external.files</spirit:envIdentifier>
        <spirit:fileSetRef>
          <spirit:localName>xilinx_externalfiles_view_fileset</spirit:localName>
        </spirit:fileSetRef>
        <spirit:parameters>
          <spirit:parameter>
            <spirit:name>GENtimestamp</spirit:name>
            <spirit:value>Wed Mar 16 11:22:53 UTC 2022</spirit:value>
          </spirit:parameter>
          <spirit:parameter>
            <spirit:name>outputProductCRC</spirit:name>
            <spirit:value>9:dc6d78a3</spirit:value>
          </spirit:parameter>
        </spirit:parameters>
      </spirit:view>
    </spirit:views>
    <spirit:ports>
      <spirit:port>
        <spirit:name>pin1_i</spirit:name>
        <spirit:wire>
          <spirit:direction>in</spirit:direction>
          <spirit:wireTypeDefs>
            <spirit:wireTypeDef>
              <spirit:typeName>std_logic</spirit:typeName>
              <spirit:viewNameRef>xilinx_anylanguagesynthesis</spirit:viewNameRef>
              <spirit:viewNameRef>xilinx_anylanguagebehavioralsimulation</spirit:viewNameRef>
            </spirit:wireTypeDef>
          </spirit:wireTypeDefs>
        </spirit:wire>
      </spirit:port>
      <spirit:port>
        <spirit:name>pin2_i</spirit:name>
        <spirit:wire>
          <spirit:direction>in</spirit:direction>
          <spirit:wireTypeDefs>
            <spirit:wireTypeDef>
              <spirit:typeName>std_logic</spirit:typeName>
              <spirit:viewNameRef>xilinx_anylanguagesynthesis</spirit:viewNameRef>
              <spirit:viewNameRef>xilinx_anylanguagebehavioralsimulation</spirit:viewNameRef>
            </spirit:wireTypeDef>
          </spirit:wireTypeDefs>
        </spirit:wire>
      </spirit:port>
      <spirit:port>
        <spirit:name>pin3_i</spirit:name>
        <spirit:wire>
          <spirit:direction>in</spirit:direction>
          <spirit:wireTypeDefs>
            <spirit:wireTypeDef>
              <spirit:typeName>std_logic</spirit:typeName>
              <spirit:viewNameRef>xilinx_anylanguagesynthesis</spirit:viewNameRef>
              <spirit:viewNameRef>xilinx_anylanguagebehavioralsimulation</spirit:viewNameRef>
            </spirit:wireTypeDef>
          </spirit:wireTypeDefs>
        </spirit:wire>
      </spirit:port>
      <spirit:port>
        <spirit:name>pin4_i</spirit:name>
        <spirit:wire>
          <spirit:direction>in</spirit:direction>
          <spirit:wireTypeDefs>
            <spirit:wireTypeDef>
              <spirit:typeName>std_logic</spirit:typeName>
              <spirit:viewNameRef>xilinx_anylanguagesynthesis</spirit:viewNameRef>
              <spirit:viewNameRef>xilinx_anylanguagebehavioralsimulation</spirit:viewNameRef>
            </spirit:wireTypeDef>
          </spirit:wireTypeDefs>
        </spirit:wire>
      </spirit:port>
      <spirit:port>
        <spirit:name>pin7_i</spirit:name>
        <spirit:wire>
          <spirit:direction>in</spirit:direction>
          <spirit:wireTypeDefs>
            <spirit:wireTypeDef>
              <spirit:typeName>std_logic</spirit:typeName>
              <spirit:viewNameRef>xilinx_anylanguagesynthesis</spirit:viewNameRef>
              <spirit:viewNameRef>xilinx_anylanguagebehavioralsimulation</spirit:viewNameRef>
            </spirit:wireTypeDef>
          </spirit:wireTypeDefs>
        </spirit:wire>
      </spirit:port>
      <spirit:port>
        <spirit:name>pin8_i</spirit:name>
        <spirit:wire>
          <spirit:direction>in</spirit:direction>
          <spirit:wireTypeDefs>
            <spirit:wireTypeDef>
              <spirit:typeName>std_logic</spirit:typeName>
              <spirit:viewNameRef>xilinx_anylanguagesynthesis</spirit:viewNameRef>
              <spirit:viewNameRef>xilinx_anylanguagebehavioralsimulation</spirit:viewNameRef>
            </spirit:wireTypeDef>
          </spirit:wireTypeDefs>
        </spirit:wire>
      </spirit:port>
      <spirit:port>
        <spirit:name>pin9_i</spirit:name>
        <spirit:wire>
          <spirit:direction>in</spirit:direction>
          <spirit:wireTypeDefs>
            <spirit:wireTypeDef>
              <spirit:typeName>std_logic</spirit:typeName>
              <spirit:viewNameRef>xilinx_anylanguagesynthesis</spirit:viewNameRef>
              <spirit:viewNameRef>xilinx_anylanguagebehavioralsimulation</spirit:viewNameRef>
            </spirit:wireTypeDef>
          </spirit:wireTypeDefs>
        </spirit:wire>
      </spirit:port>
      <spirit:port>
        <spirit:name>pin10_i</spirit:name>
        <spirit:wire>
          <spirit:direction>in</spirit:direction>
          <spirit:wireTypeDefs>
            <spirit:wireTypeDef>
              <spirit:typeName>std_logic</spirit:typeName>
              <spirit:viewNameRef>xilinx_anylanguagesynthesis</spirit:viewNameRef>
              <spirit:viewNameRef>xilinx_anylanguagebehavioralsimulation</spirit:viewNameRef>
            </spirit:wireTypeDef>
          </spirit:wireTypeDefs>
        </spirit:wire>
      </spirit:port>
      <spirit:port>
        <spirit:name>pin1_o</spirit:name>
        <spirit:wire>
          <spirit:direction>out</spirit:direction>
          <spirit:wireTypeDefs>
            <spirit:wireTypeDef>
              <spirit:typeName>std_logic</spirit:typeName>
              <spirit:viewNameRef>xilinx_anylanguagesynthesis</spirit:viewNameRef>
              <spirit:viewNameRef>xilinx_anylanguagebehavioralsimulation</spirit:viewNameRef>
            </spirit:wireTypeDef>
          </spirit:wireTypeDefs>
        </spirit:wire>
      </spirit:port>
      <spirit:port>
        <spirit:name>pin2_o</spirit:name>
        <spirit:wire>
          <spirit:direction>out</spirit:direction>
          <spirit:wireTypeDefs>
            <spirit:wireTypeDef>
              <spirit:typeName>std_logic</spirit:typeName>
              <spirit:viewNameRef>xilinx_anylanguagesynthesis</spirit:viewNameRef>
              <spirit:viewNameRef>xilinx_anylanguagebehavioralsimulation</spirit:viewNameRef>
            </spirit:wireTypeDef>
          </spirit:wireTypeDefs>
        </spirit:wire>
      </spirit:port>
      <spirit:port>
        <spirit:name>pin3_o</spirit:name>
        <spirit:wire>
          <spirit:direction>out</spirit:direction>
          <spirit:wireTypeDefs>
            <spirit:wireTypeDef>
              <spirit:typeName>std_logic</spirit:typeName>
              <spirit:viewNameRef>xilinx_anylanguagesynthesis</spirit:viewNameRef>
              <spirit:viewNameRef>xilinx_anylanguagebehavioralsimulation</spirit:viewNameRef>
            </spirit:wireTypeDef>
          </spirit:wireTypeDefs>
        </spirit:wire>
      </spirit:port>
      <spirit:port>
        <spirit:name>pin4_o</spirit:name>
        <spirit:wire>
          <spirit:direction>out</spirit:direction>
          <spirit:wireTypeDefs>
            <spirit:wireTypeDef>
              <spirit:typeName>std_logic</spirit:typeName>
              <spirit:viewNameRef>xilinx_anylanguagesynthesis</spirit:viewNameRef>
              <spirit:viewNameRef>xilinx_anylanguagebehavioralsimulation</spirit:viewNameRef>
            </spirit:wireTypeDef>
          </spirit:wireTypeDefs>
        </spirit:wire>
      </spirit:port>
      <spirit:port>
        <spirit:name>pin7_o</spirit:name>
        <spirit:wire>
          <spirit:direction>out</spirit:direction>
          <spirit:wireTypeDefs>
            <spirit:wireTypeDef>
              <spirit:typeName>std_logic</spirit:typeName>
              <spirit:viewNameRef>xilinx_anylanguagesynthesis</spirit:viewNameRef>
              <spirit:viewNameRef>xilinx_anylanguagebehavioralsimulation</spirit:viewNameRef>
            </spirit:wireTypeDef>
          </spirit:wireTypeDefs>
        </spirit:wire>
      </spirit:port>
      <spirit:port>
        <spirit:name>pin8_o</spirit:name>
        <spirit:wire>
          <spirit:direction>out</spirit:direction>
          <spirit:wireTypeDefs>
            <spirit:wireTypeDef>
              <spirit:typeName>std_logic</spirit:typeName>
              <spirit:viewNameRef>xilinx_anylanguagesynthesis</spirit:viewNameRef>
              <spirit:viewNameRef>xilinx_anylanguagebehavioralsimulation</spirit:viewNameRef>
            </spirit:wireTypeDef>
          </spirit:wireTypeDefs>
        </spirit:wire>
      </spirit:port>
      <spirit:port>
        <spirit:name>pin9_o</spirit:name>
        <spirit:wire>
          <spirit:direction>out</spirit:direction>
          <spirit:wireTypeDefs>
            <spirit:wireTypeDef>
              <spirit:typeName>std_logic</spirit:typeName>
              <spirit:viewNameRef>xilinx_anylanguagesynthesis</spirit:viewNameRef>
              <spirit:viewNameRef>xilinx_anylanguagebehavioralsimulation</spirit:viewNameRef>
            </spirit:wireTypeDef>
          </spirit:wireTypeDefs>
        </spirit:wire>
      </spirit:port>
      <spirit:port>
        <spirit:name>pin10_o</spirit:name>
        <spirit:wire>
          <spirit:direction>out</spirit:direction>
          <spirit:wireTypeDefs>
            <spirit:wireTypeDef>
              <spirit:typeName>std_logic</spirit:typeName>
              <spirit:viewNameRef>xilinx_anylanguagesynthesis</spirit:viewNameRef>
              <spirit:viewNameRef>xilinx_anylanguagebehavioralsimulation</spirit:viewNameRef>
            </spirit:wireTypeDef>
          </spirit:wireTypeDefs>
        </spirit:wire>
      </spirit:port>
      <spirit:port>
        <spirit:name>pin1_t</spirit:name>
        <spirit:wire>
          <spirit:direction>out</spirit:direction>
          <spirit:wireTypeDefs>
            <spirit:wireTypeDef>
              <spirit:typeName>std_logic</spirit:typeName>
              <spirit:viewNameRef>xilinx_anylanguagesynthesis</spirit:viewNameRef>
              <spirit:viewNameRef>xilinx_anylanguagebehavioralsimulation</spirit:viewNameRef>
            </spirit:wireTypeDef>
          </spirit:wireTypeDefs>
        </spirit:wire>
      </spirit:port>
      <spirit:port>
        <spirit:name>pin2_t</spirit:name>
        <spirit:wire>
          <spirit:direction>out</spirit:direction>
          <spirit:wireTypeDefs>
            <spirit:wireTypeDef>
              <spirit:typeName>std_logic</spirit:typeName>
              <spirit:viewNameRef>xilinx_anylanguagesynthesis</spirit:viewNameRef>
              <spirit:viewNameRef>xilinx_anylanguagebehavioralsimulation</spirit:viewNameRef>
            </spirit:wireTypeDef>
          </spirit:wireTypeDefs>
        </spirit:wire>
      </spirit:port>
      <spirit:port>
        <spirit:name>pin3_t</spirit:name>
        <spirit:wire>
          <spirit:direction>out</spirit:direction>
          <spirit:wireTypeDefs>
            <spirit:wireTypeDef>
              <spirit:typeName>std_logic</spirit:typeName>
              <spirit:viewNameRef>xilinx_anylanguagesynthesis</spirit:viewNameRef>
              <spirit:viewNameRef>xilinx_anylanguagebehavioralsimulation</spirit:viewNameRef>
            </spirit:wireTypeDef>
          </spirit:wireTypeDefs>
        </spirit:wire>
      </spirit:port>
      <spirit:port>
        <spirit:name>pin4_t</spirit:name>
        <spirit:wire>
          <spirit:direction>out</spirit:direction>
          <spirit:wireTypeDefs>
            <spirit:wireTypeDef>
              <spirit:typeName>std_logic</spirit:typeName>
              <spirit:viewNameRef>xilinx_anylanguagesynthesis</spirit:viewNameRef>
              <spirit:viewNameRef>xilinx_anylanguagebehavioralsimulation</spirit:viewNameRef>
            </spirit:wireTypeDef>
          </spirit:wireTypeDefs>
        </spirit:wire>
      </spirit:port>
      <spirit:port>
        <spirit:name>pin7_t</spirit:name>
        <spirit:wire>
          <spirit:direction>out</spirit:direction>
          <spirit:wireTypeDefs>
            <spirit:wireTypeDef>
              <spirit:typeName>std_logic</spirit:typeName>
              <spirit:viewNameRef>xilinx_anylanguagesynthesis</spirit:viewNameRef>
              <spirit:viewNameRef>xilinx_anylanguagebehavioralsimulation</spirit:viewNameRef>
            </spirit:wireTypeDef>
          </spirit:wireTypeDefs>
        </spirit:wire>
      </spirit:port>
      <spirit:port>
        <spirit:name>pin8_t</spirit:name>
        <spirit:wire>
          <spirit:direction>out</spirit:direction>
          <spirit:wireTypeDefs>
            <spirit:wireTypeDef>
              <spirit:typeName>std_logic</spirit:typeName>
              <spirit:viewNameRef>xilinx_anylanguagesynthesis</spirit:viewNameRef>
              <spirit:viewNameRef>xilinx_anylanguagebehavioralsimulation</spirit:viewNameRef>
            </spirit:wireTypeDef>
          </spirit:wireTypeDefs>
        </spirit:wire>
      </spirit:port>
      <spirit:port>
        <spirit:name>pin9_t</spirit:name>
        <spirit:wire>
          <spirit:direction>out</spirit:direction>
          <spirit:wireTypeDefs>
            <spirit:wireTypeDef>
              <spirit:typeName>std_logic</spirit:typeName>
              <spirit:viewNameRef>xilinx_anylanguagesynthesis</spirit:viewNameRef>
              <spirit:viewNameRef>xilinx_anylanguagebehavioralsimulation</spirit:viewNameRef>
            </spirit:wireTypeDef>
          </spirit:wireTypeDefs>
        </spirit:wire>
      </spirit:port>
      <spirit:port>
        <spirit:name>pin10_t</spirit:name>
        <spirit:wire>
          <spirit:direction>out</spirit:direction>
          <spirit:wireTypeDefs>
            <spirit:wireTypeDef>
              <spirit:typeName>std_logic</spirit:typeName>
              <spirit:viewNameRef>xilinx_anylanguagesynthesis</spirit:viewNameRef>
              <spirit:viewNameRef>xilinx_anylanguagebehavioralsimulation</spirit:viewNameRef>
            </spirit:wireTypeDef>
          </spirit:wireTypeDefs>
        </spirit:wire>
      </spirit:port>
      <spirit:port>
        <spirit:name>sd_cd</spirit:name>
        <spirit:wire>
          <spirit:direction>out</spirit:direction>
          <spirit:wireTypeDefs>
            <spirit:wireTypeDef>
              <spirit:typeName>std_logic</spirit:typeName>
              <spirit:viewNameRef>xilinx_anylanguagesynthesis</spirit:viewNameRef>
              <spirit:viewNameRef>xilinx_anylanguagebehavioralsimulation</spirit:viewNameRef>
            </spirit:wireTypeDef>
          </spirit:wireTypeDefs>
        </spirit:wire>
      </spirit:port>
      <spirit:port>
        <spirit:name>sd_sck</spirit:name>
        <spirit:wire>
          <spirit:direction>in</spirit:direction>
          <spirit:wireTypeDefs>
            <spirit:wireTypeDef>
              <spirit:typeName>std_logic</spirit:typeName>
              <spirit:viewNameRef>xilinx_anylanguagesynthesis</spirit:viewNameRef>
              <spirit:viewNameRef>xilinx_anylanguagebehavioralsimulation</spirit:viewNameRef>
            </spirit:wireTypeDef>
          </spirit:wireTypeDefs>
          <spirit:driver>
            <spirit:defaultValue spirit:format="long">0</spirit:defaultValue>
          </spirit:driver>
        </spirit:wire>
      </spirit:port>
      <spirit:port>
        <spirit:name>sd_cmd</spirit:name>
        <spirit:wire>
          <spirit:direction>in</spirit:direction>
          <spirit:wireTypeDefs>
            <spirit:wireTypeDef>
              <spirit:typeName>std_logic</spirit:typeName>
              <spirit:viewNameRef>xilinx_anylanguagesynthesis</spirit:viewNameRef>
              <spirit:viewNameRef>xilinx_anylanguagebehavioralsimulation</spirit:viewNameRef>
            </spirit:wireTypeDef>
          </spirit:wireTypeDefs>
        </spirit:wire>
      </spirit:port>
      <spirit:port>
        <spirit:name>sd_dat0</spirit:name>
        <spirit:wire>
          <spirit:direction>out</spirit:direction>
          <spirit:wireTypeDefs>
            <spirit:wireTypeDef>
              <spirit:typeName>std_logic</spirit:typeName>
              <spirit:viewNameRef>xilinx_anylanguagesynthesis</spirit:viewNameRef>
              <spirit:viewNameRef>xilinx_anylanguagebehavioralsimulation</spirit:viewNameRef>
            </spirit:wireTypeDef>
          </spirit:wireTypeDefs>
        </spirit:wire>
      </spirit:port>
      <spirit:port>
        <spirit:name>sd_dat1</spirit:name>
        <spirit:wire>
          <spirit:direction>in</spirit:direction>
          <spirit:wireTypeDefs>
            <spirit:wireTypeDef>
              <spirit:typeName>std_logic</spirit:typeName>
              <spirit:viewNameRef>xilinx_anylanguagesynthesis</spirit:viewNameRef>
              <spirit:viewNameRef>xilinx_anylanguagebehavioralsimulation</spirit:viewNameRef>
            </spirit:wireTypeDef>
          </spirit:wireTypeDefs>
        </spirit:wire>
      </spirit:port>
      <spirit:port>
        <spirit:name>sd_dat2</spirit:name>
        <spirit:wire>
          <spirit:direction>in</spirit:direction>
          <spirit:wireTypeDefs>
            <spirit:wireTypeDef>
              <spirit:typeName>std_logic</spirit:typeName>
              <spirit:viewNameRef>xilinx_anylanguagesynthesis</spirit:viewNameRef>
              <spirit:viewNameRef>xilinx_anylanguagebehavioralsimulation</spirit:viewNameRef>
            </spirit:wireTypeDef>
          </spirit:wireTypeDefs>
        </spirit:wire>
      </spirit:port>
      <spirit:port>
        <spirit:name>sd_dat3</spirit:name>
        <spirit:wire>
          <spirit:direction>in</spirit:direction>
          <spirit:wireTypeDefs>
            <spirit:wireTypeDef>
              <spirit:typeName>std_logic</spirit:typeName>
              <spirit:viewNameRef>xilinx_anylanguagesynthesis</spirit:viewNameRef>
              <spirit:viewNameRef>xilinx_anylanguagebehavioralsimulation</spirit:viewNameRef>
            </spirit:wireTypeDef>
          </spirit:wireTypeDefs>
        </spirit:wire>
      </spirit:port>
      <spirit:port>
        <spirit:name>sd_wp</spirit:name>
        <spirit:wire>
          <spirit:direction>out</spirit:direction>
          <spirit:wireTypeDefs>
            <spirit:wireTypeDef>
              <spirit:typeName>std_logic</spirit:typeName>
              <spirit:viewNameRef>xilinx_anylanguagesynthesis</spirit:viewNameRef>
              <spirit:viewNameRef>xilinx_anylanguagebehavioralsimulation</spirit:viewNameRef>
            </spirit:wireTypeDef>
          </spirit:wireTypeDefs>
        </spirit:wire>
        <spirit:vendorExtensions>
          <xilinx:portInfo>
            <xilinx:enablement>
              <xilinx:isEnabled xilinx:resolve="dependent" xilinx:id="PORT_ENABLEMENT.sd_wp" xilinx:dependency="not ($MicroSD)">false</xilinx:isEnabled>
            </xilinx:enablement>
          </xilinx:portInfo>
        </spirit:vendorExtensions>
      </spirit:port>
    </spirit:ports>
  </spirit:model>
  <spirit:fileSets>
    <spirit:fileSet>
      <spirit:name>xilinx_anylanguagesynthesis_view_fileset</spirit:name>
      <spirit:file>
        <spirit:name>../../ipshared/52b4/src/pmod_xsd.v</spirit:name>
        <spirit:fileType>verilogSource</spirit:fileType>
      </spirit:file>
      <spirit:file>
        <spirit:name>../../srcs/sources/new/pmod/pmod_xsd.v</spirit:name>
        <spirit:fileType>verilogSource</spirit:fileType>
      </spirit:file>
    </spirit:fileSet>
    <spirit:fileSet>
      <spirit:name>xilinx_verilogsynthesiswrapper_view_fileset</spirit:name>
      <spirit:file>
        <spirit:name>synth/zxnexys_pmod_xsd_0_0.v</spirit:name>
        <spirit:fileType>verilogSource</spirit:fileType>
        <spirit:logicalName>xil_defaultlib</spirit:logicalName>
      </spirit:file>
    </spirit:fileSet>
    <spirit:fileSet>
      <spirit:name>xilinx_anylanguagebehavioralsimulation_view_fileset</spirit:name>
      <spirit:file>
        <spirit:name>../../ipshared/52b4/src/pmod_xsd.v</spirit:name>
        <spirit:fileType>verilogSource</spirit:fileType>
      </spirit:file>
      <spirit:file>
        <spirit:name>../../srcs/sources/new/pmod/pmod_xsd.v</spirit:name>
        <spirit:fileType>verilogSource</spirit:fileType>
      </spirit:file>
    </spirit:fileSet>
    <spirit:fileSet>
      <spirit:name>xilinx_verilogsimulationwrapper_view_fileset</spirit:name>
      <spirit:file>
        <spirit:name>sim/zxnexys_pmod_xsd_0_0.v</spirit:name>
        <spirit:fileType>verilogSource</spirit:fileType>
        <spirit:logicalName>xil_defaultlib</spirit:logicalName>
      </spirit:file>
    </spirit:fileSet>
    <spirit:fileSet>
      <spirit:name>xilinx_externalfiles_view_fileset</spirit:name>
      <spirit:file>
        <spirit:name>zxnexys_pmod_xsd_0_0.dcp</spirit:name>
        <spirit:userFileType>dcp</spirit:userFileType>
        <spirit:userFileType>USED_IN_implementation</spirit:userFileType>
        <spirit:userFileType>USED_IN_synthesis</spirit:userFileType>
        <spirit:logicalName>xil_defaultlib</spirit:logicalName>
      </spirit:file>
      <spirit:file>
        <spirit:name>zxnexys_pmod_xsd_0_0_stub.v</spirit:name>
        <spirit:fileType>verilogSource</spirit:fileType>
        <spirit:userFileType>USED_IN_synth_blackbox_stub</spirit:userFileType>
        <spirit:logicalName>xil_defaultlib</spirit:logicalName>
      </spirit:file>
      <spirit:file>
        <spirit:name>zxnexys_pmod_xsd_0_0_stub.vhdl</spirit:name>
        <spirit:fileType>vhdlSource</spirit:fileType>
        <spirit:userFileType>USED_IN_synth_blackbox_stub</spirit:userFileType>
        <spirit:logicalName>xil_defaultlib</spirit:logicalName>
      </spirit:file>
      <spirit:file>
        <spirit:name>zxnexys_pmod_xsd_0_0_sim_netlist.v</spirit:name>
        <spirit:fileType>verilogSource</spirit:fileType>
        <spirit:userFileType>USED_IN_simulation</spirit:userFileType>
        <spirit:userFileType>USED_IN_single_language</spirit:userFileType>
        <spirit:logicalName>xil_defaultlib</spirit:logicalName>
      </spirit:file>
      <spirit:file>
        <spirit:name>zxnexys_pmod_xsd_0_0_sim_netlist.vhdl</spirit:name>
        <spirit:fileType>vhdlSource</spirit:fileType>
        <spirit:userFileType>USED_IN_simulation</spirit:userFileType>
        <spirit:userFileType>USED_IN_single_language</spirit:userFileType>
        <spirit:logicalName>xil_defaultlib</spirit:logicalName>
      </spirit:file>
    </spirit:fileSet>
  </spirit:fileSets>
  <spirit:description>pmod_xsd_v1_1</spirit:description>
  <spirit:parameters>
    <spirit:parameter>
      <spirit:name>Component_Name</spirit:name>
      <spirit:value spirit:resolve="user" spirit:id="PARAM_VALUE.Component_Name" spirit:order="1">zxnexys_pmod_xsd_0_0</spirit:value>
    </spirit:parameter>
    <spirit:parameter>
      <spirit:name>MicroSD</spirit:name>
      <spirit:displayName>Microsd</spirit:displayName>
      <spirit:value spirit:format="bool" spirit:resolve="user" spirit:id="PARAM_VALUE.MicroSD">true</spirit:value>
    </spirit:parameter>
  </spirit:parameters>
  <spirit:vendorExtensions>
    <xilinx:coreExtensions>
      <xilinx:displayName>pmod_xsd_v1_1</xilinx:displayName>
      <xilinx:definitionSource>package_project</xilinx:definitionSource>
      <xilinx:coreRevision>4</xilinx:coreRevision>
      <xilinx:tags>
        <xilinx:tag xilinx:name="ui.data.coregen.df@6cbc3617_ARCHIVE_LOCATION">v:/ip/pmod_xsd</xilinx:tag>
        <xilinx:tag xilinx:name="ui.data.coregen.df@244c8969_ARCHIVE_LOCATION">v:/ip/pmod_xsd</xilinx:tag>
        <xilinx:tag xilinx:name="ui.data.coregen.df@5f2eeed6_ARCHIVE_LOCATION">v:/ip/pmod_xsd</xilinx:tag>
        <xilinx:tag xilinx:name="ui.data.coregen.df@19b5ff14_ARCHIVE_LOCATION">v:/ip/pmod_xsd</xilinx:tag>
        <xilinx:tag xilinx:name="ui.data.coregen.df@678786b_ARCHIVE_LOCATION">v:/ip/pmod_xsd</xilinx:tag>
        <xilinx:tag xilinx:name="ui.data.coregen.df@366041db_ARCHIVE_LOCATION">v:/ip/pmod_xsd</xilinx:tag>
        <xilinx:tag xilinx:name="ui.data.coregen.df@1b1a56b8_ARCHIVE_LOCATION">v:/ip/pmod_xsd</xilinx:tag>
        <xilinx:tag xilinx:name="ui.data.coregen.df@43272a88_ARCHIVE_LOCATION">v:/ip/pmod_xsd</xilinx:tag>
        <xilinx:tag xilinx:name="ui.data.coregen.df@546eeccf_ARCHIVE_LOCATION">v:/ip/pmod_xsd</xilinx:tag>
        <xilinx:tag xilinx:name="ui.data.coregen.df@418c3641_ARCHIVE_LOCATION">v:/ip/pmod_xsd</xilinx:tag>
        <xilinx:tag xilinx:name="ui.data.coregen.df@5e3828b6_ARCHIVE_LOCATION">v:/ip/pmod_xsd</xilinx:tag>
        <xilinx:tag xilinx:name="ui.data.coregen.df@2d3eb3bf_ARCHIVE_LOCATION">v:/ip/pmod_xsd</xilinx:tag>
        <xilinx:tag xilinx:name="ui.data.coregen.df@18fbc4ed_ARCHIVE_LOCATION">v:/ip/pmod_xsd</xilinx:tag>
        <xilinx:tag xilinx:name="ui.data.coregen.df@7941b830_ARCHIVE_LOCATION">v:/ip/pmod_xsd</xilinx:tag>
        <xilinx:tag xilinx:name="ui.data.coregen.df@235f6bfc_ARCHIVE_LOCATION">v:/ip/pmod_xsd</xilinx:tag>
        <xilinx:tag xilinx:name="ui.data.coregen.df@4ae7df79_ARCHIVE_LOCATION">v:/ip/pmod_xsd</xilinx:tag>
        <xilinx:tag xilinx:name="ui.data.coregen.df@5479a44c_ARCHIVE_LOCATION">v:/ip/pmod_xsd</xilinx:tag>
        <xilinx:tag xilinx:name="ui.data.coregen.df@881e169_ARCHIVE_LOCATION">v:/ip/pmod_xsd</xilinx:tag>
        <xilinx:tag xilinx:name="ui.data.coregen.df@5265eed5_ARCHIVE_LOCATION">v:/ip/pmod_xsd</xilinx:tag>
        <xilinx:tag xilinx:name="ui.data.coregen.df@302026fa_ARCHIVE_LOCATION">v:/ip/pmod_xsd</xilinx:tag>
        <xilinx:tag xilinx:name="ui.data.coregen.df@bf0c66c_ARCHIVE_LOCATION">v:/ip/pmod_xsd</xilinx:tag>
        <xilinx:tag xilinx:name="ui.data.coregen.df@31aeab85_ARCHIVE_LOCATION">v:/ip/pmod_xsd</xilinx:tag>
        <xilinx:tag xilinx:name="ui.data.coregen.df@38ec7b1b_ARCHIVE_LOCATION">v:/ip/pmod_xsd</xilinx:tag>
        <xilinx:tag xilinx:name="ui.data.coregen.df@33d3ff94_ARCHIVE_LOCATION">v:/ip/pmod_xsd</xilinx:tag>
        <xilinx:tag xilinx:name="ui.data.coregen.df@1c05b30b_ARCHIVE_LOCATION">v:/ip/pmod_xsd</xilinx:tag>
        <xilinx:tag xilinx:name="ui.data.coregen.df@55477173_ARCHIVE_LOCATION">v:/ip/pmod_xsd</xilinx:tag>
        <xilinx:tag xilinx:name="ui.data.coregen.df@755b7596_ARCHIVE_LOCATION">v:/ip/pmod_xsd</xilinx:tag>
        <xilinx:tag xilinx:name="ui.data.coregen.df@39eb3575_ARCHIVE_LOCATION">v:/ip/pmod_xsd</xilinx:tag>
        <xilinx:tag xilinx:name="ui.data.coregen.df@3ce06609_ARCHIVE_LOCATION">v:/ip/pmod_xsd</xilinx:tag>
        <xilinx:tag xilinx:name="ui.data.coregen.df@1695902_ARCHIVE_LOCATION">v:/ip/pmod_xsd</xilinx:tag>
        <xilinx:tag xilinx:name="ui.data.coregen.df@61b2fb31_ARCHIVE_LOCATION">v:/ip/pmod_xsd</xilinx:tag>
        <xilinx:tag xilinx:name="ui.data.coregen.df@47b93e8_ARCHIVE_LOCATION">v:/ip/pmod_xsd</xilinx:tag>
        <xilinx:tag xilinx:name="ui.data.coregen.df@1afb9905_ARCHIVE_LOCATION">v:/ip/pmod_xsd</xilinx:tag>
        <xilinx:tag xilinx:name="ui.data.coregen.df@39ff3214_ARCHIVE_LOCATION">v:/ip/pmod_xsd</xilinx:tag>
        <xilinx:tag xilinx:name="ui.data.coregen.df@56b3a53f_ARCHIVE_LOCATION">v:/ip/pmod_xsd</xilinx:tag>
        <xilinx:tag xilinx:name="ui.data.coregen.df@49bbde57_ARCHIVE_LOCATION">v:/ip/pmod_xsd</xilinx:tag>
      </xilinx:tags>
    </xilinx:coreExtensions>
    <xilinx:packagingInfo>
      <xilinx:xilinxVersion>2021.2</xilinx:xilinxVersion>
      <xilinx:checksum xilinx:scope="busInterfaces" xilinx:value="28f2cbec"/>
      <xilinx:checksum xilinx:scope="fileGroups" xilinx:value="e2cfb547"/>
      <xilinx:checksum xilinx:scope="ports" xilinx:value="e2f645b5"/>
      <xilinx:checksum xilinx:scope="parameters" xilinx:value="7155a24c"/>
    </xilinx:packagingInfo>
  </spirit:vendorExtensions>
</spirit:component>
